  0           0 RESUME                   0

  1           2 PUSH_NULL
              4 LOAD_NAME                0 (input)
              6 LOAD_CONST               0 ('Enter THE password: ')
              8 PRECALL                  1
             12 CALL                     1
             22 STORE_NAME               1 (pw)

  3          24 LOAD_NAME                1 (pw)
             26 LOAD_METHOD              2 (isalnum)
             48 PRECALL                  0
             52 CALL                     0
             62 POP_JUMP_FORWARD_IF_TRUE    21 (to 106)

  4          64 PUSH_NULL
             66 LOAD_NAME                3 (print)
             68 LOAD_CONST               1 ('Password format is not valid!')
             70 PRECALL                  1
             74 CALL                     1
             84 POP_TOP

  5          86 PUSH_NULL
             88 LOAD_NAME                4 (exit)
             90 PRECALL                  0
             94 CALL                     0
            104 POP_TOP

  7     >>  106 PUSH_NULL
            108 LOAD_NAME                5 (len)
            110 LOAD_NAME                1 (pw)
            112 PRECALL                  1
            116 CALL                     1
            126 LOAD_CONST               2 (9)
            128 COMPARE_OP               4 (>)
            134 POP_JUMP_FORWARD_IF_FALSE    21 (to 178)

  8         136 PUSH_NULL
            138 LOAD_NAME                3 (print)
            140 LOAD_CONST               3 ('Password is too long!')
            142 PRECALL                  1
            146 CALL                     1
            156 POP_TOP

  9         158 PUSH_NULL
            160 LOAD_NAME                4 (exit)
            162 PRECALL                  0
            166 CALL                     0
            176 POP_TOP

 11     >>  178 PUSH_NULL
            180 LOAD_NAME                5 (len)
            182 LOAD_NAME                1 (pw)
            184 PRECALL                  1
            188 CALL                     1
            198 LOAD_CONST               2 (9)
            200 COMPARE_OP               0 (<)
            206 POP_JUMP_FORWARD_IF_FALSE    21 (to 250)

 12         208 PUSH_NULL
            210 LOAD_NAME                3 (print)
            212 LOAD_CONST               4 ('Password is too short!')
            214 PRECALL                  1
            218 CALL                     1
            228 POP_TOP

 13         230 PUSH_NULL
            232 LOAD_NAME                4 (exit)
            234 PRECALL                  0
            238 CALL                     0
            248 POP_TOP

 15     >>  250 BUILD_LIST               0
            252 LOAD_CONST               5 ((0, 0, 0, 0, 0, 0, 0, 0, 0))
            254 LIST_EXTEND              1
            256 STORE_NAME               6 (x)

 16         258 PUSH_NULL
            260 LOAD_NAME                7 (range)
            262 LOAD_CONST               2 (9)
            264 PRECALL                  1
            268 CALL                     1
            278 GET_ITER
        >>  280 FOR_ITER                37 (to 356)
            282 STORE_NAME               8 (i)

 17         284 PUSH_NULL
            286 LOAD_NAME                9 (ord)
            288 LOAD_NAME                1 (pw)
            290 LOAD_NAME                8 (i)
            292 BINARY_SUBSCR
            302 PRECALL                  1
            306 CALL                     1
            316 LOAD_NAME                6 (x)
            318 PUSH_NULL
            320 LOAD_NAME                5 (len)
            322 LOAD_NAME                6 (x)
            324 PRECALL                  1
            328 CALL                     1
            338 LOAD_NAME                8 (i)
            340 BINARY_OP               10 (-)
            344 LOAD_CONST               6 (1)
            346 BINARY_OP               10 (-)
            350 STORE_SUBSCR
            354 JUMP_BACKWARD           38 (to 280)

 19     >>  356 PUSH_NULL
            358 LOAD_NAME                3 (print)
            360 LOAD_NAME                6 (x)
            362 PRECALL                  1
            366 CALL                     1
            376 POP_TOP

 21         378 LOAD_NAME                6 (x)
            380 LOAD_CONST               7 (7)
            382 BINARY_SUBSCR
            392 LOAD_CONST               8 (69)
            394 BINARY_OP                0 (+)
            398 LOAD_CONST               9 (120)
            400 COMPARE_OP               2 (==)
            406 POP_JUMP_FORWARD_IF_FALSE   174 (to 756)

 22         408 LOAD_NAME                6 (x)
            410 LOAD_CONST              10 (3)
            412 BINARY_SUBSCR
            422 LOAD_CONST              11 (1337)
            424 BINARY_OP               12 (^)
            428 LOAD_CONST              12 (1355)
            430 COMPARE_OP               2 (==)
            436 POP_JUMP_FORWARD_IF_FALSE   159 (to 756)

 23         438 LOAD_NAME                6 (x)
            440 LOAD_CONST              13 (0)
            442 BINARY_SUBSCR
            452 LOAD_CONST              14 (22)
            454 BINARY_OP                2 (//)
            458 LOAD_CONST              15 (5)
            460 COMPARE_OP               2 (==)
            466 POP_JUMP_FORWARD_IF_FALSE   144 (to 756)

 24         468 LOAD_NAME                6 (x)
            470 LOAD_CONST              16 (4)
            472 BINARY_SUBSCR
            482 LOAD_CONST              17 (16)
            484 BINARY_OP               10 (-)
            488 LOAD_CONST              18 (35)
            490 COMPARE_OP               2 (==)
            496 POP_JUMP_FORWARD_IF_FALSE   129 (to 756)

 25         498 LOAD_NAME                6 (x)
            500 LOAD_CONST              19 (8)
            502 BINARY_SUBSCR
            512 LOAD_CONST              10 (3)
            514 BINARY_OP                3 (<<)
            518 LOAD_CONST              20 (832)
            520 COMPARE_OP               2 (==)
            526 POP_JUMP_FORWARD_IF_FALSE   114 (to 756)

 26         528 LOAD_NAME                6 (x)
            530 LOAD_CONST               6 (1)
            532 BINARY_SUBSCR
            542 LOAD_CONST              21 (2)
            544 BINARY_OP                8 (**)
            548 LOAD_CONST              22 (9409)
            550 COMPARE_OP               2 (==)
            556 POP_JUMP_FORWARD_IF_FALSE    99 (to 756)

 27         558 LOAD_NAME                6 (x)
            560 LOAD_CONST              23 (6)
            562 BINARY_SUBSCR
            572 LOAD_CONST               7 (7)
            574 BINARY_OP                5 (*)
            578 LOAD_CONST              24 (693)
            580 COMPARE_OP               2 (==)
            586 POP_JUMP_FORWARD_IF_FALSE    84 (to 756)

 28         588 LOAD_NAME                6 (x)
            590 LOAD_CONST              21 (2)
            592 BINARY_SUBSCR
            602 UNARY_INVERT
            604 LOAD_CONST              25 (-110)
            606 COMPARE_OP               2 (==)
            612 POP_JUMP_FORWARD_IF_FALSE    71 (to 756)

 29         614 LOAD_NAME                6 (x)
            616 LOAD_CONST              15 (5)
            618 BINARY_SUBSCR
            628 LOAD_CONST              26 (107)
            630 COMPARE_OP               2 (==)
            636 POP_JUMP_FORWARD_IF_FALSE    59 (to 756)

 30         638 PUSH_NULL
            640 LOAD_NAME                3 (print)
            642 LOAD_CONST              27 ("Correct! Here's your flag: ")
            644 PRECALL                  1
            648 CALL                     1
            658 POP_TOP

 31         660 PUSH_NULL
            662 LOAD_NAME                3 (print)
            664 PUSH_NULL
            666 LOAD_NAME               10 (open)
            668 LOAD_CONST              28 ('flag.txt')
            670 PRECALL                  1
            674 CALL                     1
            684 LOAD_METHOD             11 (read)
            706 PRECALL                  0
            710 CALL                     0
            720 PRECALL                  1
            724 CALL                     1
            734 POP_TOP

 32         736 PUSH_NULL
            738 LOAD_NAME                4 (exit)
            740 PRECALL                  0
            744 CALL                     0
            754 POP_TOP

 34     >>  756 PUSH_NULL
            758 LOAD_NAME                3 (print)
            760 LOAD_CONST              29 ('Wrong password.')
            762 PRECALL                  1
            766 CALL                     1
            776 POP_TOP
            778 LOAD_CONST              30 (None)
            780 RETURN_VALUE
