0 LOAD_CONST 0 (0)
2 LOAD_CONST 1 (None)
4 IMPORT_NAME 0 (winreg)
6 STORE_NAME 0 (winreg)

8 LOAD_CONST 0 (0)
10 LOAD_CONST 1 (None)
12 IMPORT_NAME 1 (subprocess)
14 STORE_NAME 1 (subprocess)

16 LOAD_CONST 0 (0)
18 LOAD_CONST 1 (None)
20 IMPORT_NAME 2 (sys)
22 STORE_NAME 2 (sys)

24 LOAD_CONST 0 (0)
26 LOAD_CONST 1 (None)
28 IMPORT_NAME 3 (os)
30 STORE_NAME 3 (os)

32 LOAD_CONST 0 (0)
34 LOAD_CONST 1 (None)
36 IMPORT_NAME 4 (random)
38 STORE_NAME 4 (random)

40 LOAD_CONST 0 (0)
42 LOAD_CONST 1 (None)
44 IMPORT_NAME 5 (string)
46 STORE_NAME 5 (string)

48 LOAD_CONST 0 (0)
50 LOAD_CONST 1 (None)
52 IMPORT_NAME 6 (json)
54 STORE_NAME 6 (json)

56 LOAD_BUILD_CLASS
58 PUSH_NULL
60 LOAD_CONST 2 (code object RegistryManager)
62 MAKE_FUNCTION
64 LOAD_CONST 3 ("RegistryManager")
66 CALL 2
68 STORE_NAME 7 (RegistryManager)

70 LOAD_CONST 4 (code object main)
72 MAKE_FUNCTION
74 STORE_NAME 8 (main)

76 LOAD_CONST 7 ((True,))
78 LOAD_CONST 5 (code object destruction)
80 MAKE_FUNCTION
82 SET_FUNCTION_ATTRIBUTE 1
84 STORE_NAME 9 (destruction)

86 LOAD_NAME 10 (__name__)
88 LOAD_CONST 6 ("__main__")
90 COMPARE_OP 88 (==)
92 POP_JUMP_IF_FALSE 8 (to 102)

94 LOAD_NAME 8 (main)
96 PUSH_NULL
98 CALL 0
100 POP_TOP
102 RETURN_CONST 1 (None)

104 RETURN_CONST 1 (None)


0 LOAD_NAME 0 (__name__)
2 STORE_NAME 1 (__module__)
4 LOAD_CONST 0 ("RegistryManager")
6 STORE_NAME 2 (__qualname__)
8 LOAD_CONST 1 (13)
10 STORE_NAME 3 (__firstlineno__)

12 LOAD_CONST 2 (code object __init__)
14 MAKE_FUNCTION
16 STORE_NAME 4 (__init__)

18 LOAD_CONST 3 (code object _ensure_base_exists)
20 MAKE_FUNCTION
22 STORE_NAME 5 (_ensure_base_exists)

24 LOAD_CONST 4 (code object set)
26 MAKE_FUNCTION
28 STORE_NAME 6 (set)

30 LOAD_CONST 5 (code object u2s)
32 MAKE_FUNCTION
34 STORE_NAME 7 (u2s)

36 LOAD_CONST 10 ((None,))
38 LOAD_CONST 7 (code object get)
40 MAKE_FUNCTION
42 SET_FUNCTION_ATTRIBUTE 1
44 STORE_NAME 8 (get)

46 LOAD_CONST 8 (code object delete)
48 MAKE_FUNCTION
50 STORE_NAME 9 (delete)
52 LOAD_CONST 9 (('base_path', 'root'))
54 STORE_NAME 10 (__static_attributes__)
56 RETURN_CONST 6 (None)


0 LOAD_GLOBAL 0 (winreg)
2 LOAD_ATTR 2 (HKEY_CURRENT_USER)
4 LOAD_FAST 0 (self)
6 STORE_ATTR 2 (root)

8 LOAD_CONST 1 ("Software\\OneShot")
10 LOAD_FAST 0 (self)
12 STORE_ATTR 3 (base_path)

14 LOAD_FAST 0 (self)
16 LOAD_ATTR 9 (NULL|self + _ensure_base_exists)
18 CALL 0
20 POP_TOP
22 RETURN_CONST 0 (None)


0 NOP

2 LOAD_GLOBAL 0 (winreg)
4 LOAD_ATTR 2 (CreateKey)
6 PUSH_NULL
8 LOAD_FAST 0 (self)
10 LOAD_ATTR 4 (root)
12 LOAD_FAST 0 (self)
14 LOAD_ATTR 6 (base_path)
16 CALL 2
18 POP_TOP
20 RETURN_CONST 0 (None)
22 PUSH_EXC_INFO

24 POP_TOP

26 POP_EXCEPT
28 RETURN_CONST 0 (None)
30 COPY 3
32 POP_EXCEPT
34 RERAISE 1


0 NOP

2 LOAD_GLOBAL 0 (winreg)
4 LOAD_ATTR 2 (CreateKey)
6 PUSH_NULL
8 LOAD_FAST 0 (self)
10 LOAD_ATTR 4 (root)
12 LOAD_FAST 0 (self)
14 LOAD_ATTR 6 (base_path)
16 CALL 2
18 STORE_FAST 3 (key)

20 NOP

22 LOAD_GLOBAL 9 (NULL + isinstance)
24 LOAD_FAST 2 (value)
26 LOAD_GLOBAL 10 (int)
28 CALL 2
30 TO_BOOL
32 POP_JUMP_IF_FALSE 108 (to 108)

34 LOAD_CONST 1 (-2147483648)
36 LOAD_FAST 2 (value)
38 SWAP 2
40 COPY 2
42 COMPARE_OP 58 (<=)
44 POP_JUMP_IF_FALSE 6 (to 52)
46 LOAD_CONST 2 (2147483647)
48 COMPARE_OP 58 (<=)
50 POP_JUMP_IF_FALSE 46 (to 82)
52 JUMP_FORWARD 2 (to 58)
54 POP_TOP
56 JUMP_FORWARD 43 (to 84)

58 LOAD_GLOBAL 0 (winreg)
60 LOAD_ATTR 12 (SetValueEx)
62 PUSH_NULL
64 LOAD_FAST_LOAD_FAST 49 (key, name)
66 LOAD_CONST 3 (0)
68 LOAD_GLOBAL 0 (winreg)
70 LOAD_ATTR 14 (REG_DWORD)
72 LOAD_FAST 2 (value)
74 LOAD_CONST 4 (4294967295L)
76 BINARY_OP 1 (&)
78 CALL 5
80 POP_TOP
82 JUMP_FORWARD 247 (to 224)

84 LOAD_GLOBAL 0 (winreg)
86 LOAD_ATTR 12 (SetValueEx)
88 PUSH_NULL
90 LOAD_FAST_LOAD_FAST 49 (key, name)
92 LOAD_CONST 3 (0)
94 LOAD_GLOBAL 0 (winreg)
96 LOAD_ATTR 16 (REG_SZ)
98 LOAD_GLOBAL 19 (NULL + hex)
100 LOAD_FAST 2 (value)
102 CALL 1
104 CALL 5
106 POP_TOP
108 JUMP_FORWARD 198 (to 224)

110 LOAD_GLOBAL 9 (NULL + isinstance)
112 LOAD_FAST 2 (value)
114 LOAD_GLOBAL 20 (bytes)
116 CALL 2
118 TO_BOOL
120 POP_JUMP_IF_FALSE 40 (to 142)

122 LOAD_GLOBAL 0 (winreg)
124 LOAD_ATTR 12 (SetValueEx)
126 PUSH_NULL
128 LOAD_FAST_LOAD_FAST 49 (key, name)
130 LOAD_CONST 3 (0)
132 LOAD_GLOBAL 0 (winreg)
134 LOAD_ATTR 22 (REG_BINARY)
136 LOAD_FAST 2 (value)
138 CALL 5
140 POP_TOP
142 JUMP_FORWARD 137 (to 224)

144 LOAD_GLOBAL 9 (NULL + isinstance)
146 LOAD_FAST 2 (value)
148 LOAD_GLOBAL 24 (list)
150 LOAD_GLOBAL 26 (dict)
152 BUILD_TUPLE 2
154 CALL 2
156 TO_BOOL
158 POP_JUMP_IF_FALSE 62 (to 198)

160 LOAD_GLOBAL 28 (json)
162 LOAD_ATTR 30 (dumps)
164 PUSH_NULL
166 LOAD_FAST 2 (value)
168 LOAD_CONST 5 (code object <lambda>)
170 MAKE_FUNCTION
172 LOAD_CONST 6 (('default',))
174 CALL_KW 2
176 STORE_FAST 4 (serialized)

178 LOAD_GLOBAL 0 (winreg)
180 LOAD_ATTR 12 (SetValueEx)
182 PUSH_NULL
184 LOAD_FAST_LOAD_FAST 49 (key, name)
186 LOAD_CONST 3 (0)
188 LOAD_GLOBAL 0 (winreg)
190 LOAD_ATTR 16 (REG_SZ)
192 LOAD_FAST 4 (serialized)
194 CALL 5
196 POP_TOP
198 JUMP_FORWARD 48 (to 224)

200 LOAD_GLOBAL 0 (winreg)
202 LOAD_ATTR 12 (SetValueEx)
204 PUSH_NULL
206 LOAD_FAST_LOAD_FAST 49 (key, name)
208 LOAD_CONST 3 (0)
210 LOAD_GLOBAL 0 (winreg)
212 LOAD_ATTR 16 (REG_SZ)
214 LOAD_GLOBAL 33 (NULL + str)
216 LOAD_FAST 2 (value)
218 CALL 1
220 CALL 5
222 POP_TOP

224 LOAD_GLOBAL 0 (winreg)
226 LOAD_ATTR 34 (CloseKey)
228 PUSH_NULL
230 LOAD_FAST 3 (key)
232 CALL 1
234 POP_TOP
236 RETURN_CONST 0 (None)
238 PUSH_EXC_INFO

240 LOAD_GLOBAL 0 (winreg)
242 LOAD_ATTR 34 (CloseKey)
244 PUSH_NULL
246 LOAD_FAST 3 (key)
248 CALL 1
250 POP_TOP
252 RERAISE 0
254 COPY 3
256 POP_EXCEPT
258 RERAISE 1
260 PUSH_EXC_INFO

262 LOAD_GLOBAL 36 (WindowsError)
264 CHECK_EXC_MATCH
266 POP_JUMP_IF_FALSE 22 (to 296)
268 STORE_FAST 5 (e)

270 LOAD_GLOBAL 37 (NULL + WindowsError)
272 LOAD_CONST 7 ("Failed to set ")
274 LOAD_FAST 1 (name)
276 FORMAT_SIMPLE
278 LOAD_CONST 8 (": ")
280 LOAD_FAST 5 (e)
282 FORMAT_SIMPLE
284 BUILD_STRING 4
286 CALL 1
288 RAISE_VARARGS 1 (exception instance)
290 LOAD_CONST 0 (None)
292 STORE_FAST 5 (e)
294 DELETE_FAST 5 (e)
296 RERAISE 1

298 RERAISE 0
300 COPY 3
302 POP_EXCEPT
304 RERAISE 1


0 LOAD_GLOBAL 1 (NULL + isinstance)
2 LOAD_FAST 0 (x)
4 LOAD_GLOBAL 2 (bytes)
6 CALL 2
8 TO_BOOL
10 POP_JUMP_IF_FALSE 16 (to 18)
12 LOAD_FAST 0 (x)
14 LOAD_ATTR 5 (NULL|self + hex)
16 CALL 0
18 RETURN_VALUE
20 LOAD_GLOBAL 7 (NULL + str)
22 LOAD_FAST 0 (x)
24 CALL 1
26 RETURN_VALUE


0 LOAD_FAST 1 (v)
2 LOAD_CONST 1 (2147483647)
4 COMPARE_OP 148 (>)
6 POP_JUMP_IF_FALSE 5 (to 14)

8 LOAD_FAST 1 (v)
10 LOAD_CONST 2 (4294967296L)
12 BINARY_OP 10 (-)
14 RETURN_VALUE

16 LOAD_FAST 1 (v)
18 RETURN_VALUE


0 NOP

2 LOAD_GLOBAL 0 (winreg)
4 LOAD_ATTR 2 (OpenKey)
6 PUSH_NULL
8 LOAD_FAST 0 (self)
10 LOAD_ATTR 4 (root)
12 LOAD_FAST 0 (self)
14 LOAD_ATTR 6 (base_path)
16 LOAD_CONST 1 (0)
18 LOAD_GLOBAL 0 (winreg)
20 LOAD_ATTR 8 (KEY_READ)
22 CALL 4
24 STORE_FAST 3 (key)

26 NOP

28 LOAD_GLOBAL 0 (winreg)
30 LOAD_ATTR 10 (QueryValueEx)
32 PUSH_NULL
34 LOAD_FAST_LOAD_FAST 49 (key, name)
36 CALL 2
38 UNPACK_SEQUENCE 2
40 STORE_FAST_STORE_FAST 69 (value, regtype)

42 LOAD_FAST 5 (regtype)
44 LOAD_GLOBAL 0 (winreg)
46 LOAD_ATTR 12 (REG_DWORD)
48 COMPARE_OP 88 (==)
50 POP_JUMP_IF_FALSE 18 (to 62)

52 LOAD_FAST 0 (self)
54 LOAD_ATTR 15 (NULL|self + u2s)
56 LOAD_FAST 4 (value)
58 CALL 1
60 STORE_FAST 4 (value)
62 JUMP_FORWARD 246 (to 230)

64 LOAD_FAST 5 (regtype)
66 LOAD_GLOBAL 0 (winreg)
68 LOAD_ATTR 16 (REG_SZ)
70 COMPARE_OP 88 (==)
72 POP_JUMP_IF_FALSE 35 (to 96)
74 LOAD_FAST 4 (value)
76 LOAD_ATTR 19 (NULL|self + startswith)
78 LOAD_CONST 2 ("0x")
80 CALL 1
82 TO_BOOL
84 POP_JUMP_IF_FALSE 13 (to 96)

86 LOAD_GLOBAL 21 (NULL + int)
88 LOAD_FAST 4 (value)
90 LOAD_CONST 3 (16)
92 CALL 2
94 STORE_FAST 4 (value)
96 JUMP_FORWARD 191 (to 230)

98 LOAD_FAST 5 (regtype)
100 LOAD_GLOBAL 0 (winreg)
102 LOAD_ATTR 16 (REG_SZ)
104 COMPARE_OP 88 (==)
106 POP_JUMP_IF_FALSE 171 (to 228)
108 LOAD_FAST 4 (value)
110 LOAD_ATTR 19 (NULL|self + startswith)
112 LOAD_CONST 4 ("[")
114 CALL 1
116 TO_BOOL
118 POP_JUMP_IF_TRUE 22 (to 132)
120 LOAD_FAST 4 (value)
122 LOAD_ATTR 19 (NULL|self + startswith)
124 LOAD_CONST 5 ("{")
126 CALL 1
128 TO_BOOL
130 POP_JUMP_IF_FALSE 127 (to 228)

132 NOP

134 LOAD_GLOBAL 22 (json)
136 LOAD_ATTR 24 (loads)
138 PUSH_NULL
140 LOAD_FAST 4 (value)
142 CALL 1
144 STORE_FAST 4 (value)

146 LOAD_GLOBAL 27 (NULL + isinstance)
148 LOAD_FAST 4 (value)
150 LOAD_GLOBAL 28 (list)
152 CALL 2
154 TO_BOOL
156 POP_JUMP_IF_FALSE 83 (to 228)

158 LOAD_FAST 4 (value)
160 GET_ITER
162 LOAD_FAST_AND_CLEAR 6 (item)
164 SWAP 2
166 BUILD_LIST 0
168 SWAP 2
170 GET_ITER
172 FOR_ITER 70 (to 222)
174 STORE_FAST 6 (item)
176 LOAD_GLOBAL 27 (NULL + isinstance)
178 LOAD_FAST 6 (item)
180 LOAD_GLOBAL 30 (str)
182 CALL 2
184 TO_BOOL
186 POP_JUMP_IF_FALSE 44 (to 214)
188 LOAD_GLOBAL 33 (NULL + all)
190 LOAD_CONST 6 (code object <genexpr>)
192 MAKE_FUNCTION
194 LOAD_FAST 6 (item)
196 GET_ITER
198 CALL 0
200 CALL 1
202 TO_BOOL
204 POP_JUMP_IF_FALSE 21 (to 214)
206 LOAD_GLOBAL 34 (bytes)
208 LOAD_ATTR 37 (NULL|self + fromhex)
210 LOAD_FAST 6 (item)
212 CALL 1
214 JUMP_FORWARD 1 (to 218)
216 LOAD_FAST 6 (item)
218 LIST_APPEND 2
220 JUMP_BACKWARD 72 (to 170)
222 END_FOR
224 POP_TOP
226 STORE_FAST 4 (value)
228 STORE_FAST 6 (item)

230 LOAD_FAST 4 (value)

232 LOAD_GLOBAL 0 (winreg)
234 LOAD_ATTR 40 (CloseKey)
236 PUSH_NULL
238 LOAD_FAST 3 (key)
240 CALL 1
242 POP_TOP
244 RETURN_VALUE
246 SWAP 2
248 POP_TOP

250 SWAP 2
252 STORE_FAST 6 (item)
254 RERAISE 0
256 PUSH_EXC_INFO

258 LOAD_GLOBAL 22 (json)
260 LOAD_ATTR 38 (JSONDecodeError)
262 CHECK_EXC_MATCH
264 POP_JUMP_IF_FALSE 3 (to 270)
266 POP_TOP

268 POP_EXCEPT
270 JUMP_BACKWARD_NO_INTERRUPT 51 (to 230)

272 RERAISE 0
274 COPY 3
276 POP_EXCEPT
278 RERAISE 1
280 PUSH_EXC_INFO

282 LOAD_GLOBAL 0 (winreg)
284 LOAD_ATTR 40 (CloseKey)
286 PUSH_NULL
288 LOAD_FAST 3 (key)
290 CALL 1
292 POP_TOP
294 RERAISE 0
296 COPY 3
298 POP_EXCEPT
300 RERAISE 1
302 PUSH_EXC_INFO

304 LOAD_GLOBAL 42 (WindowsError)
306 CHECK_EXC_MATCH
308 POP_JUMP_IF_FALSE 5 (to 318)
310 POP_TOP

312 LOAD_FAST 2 (default)
314 SWAP 2
316 POP_EXCEPT
318 RETURN_VALUE

320 RERAISE 0
322 COPY 3
324 POP_EXCEPT
326 RERAISE 1


0 RETURN_GENERATOR
2 POP_TOP
4 LOAD_FAST 0 (.0)
6 GET_ITER
8 FOR_ITER 9 (to 22)
10 STORE_FAST_LOAD_FAST 17 (c, c)
12 LOAD_CONST 0 ("0123456789abcdef")
14 CONTAINS_OP 0 (in)
16 YIELD_VALUE 0
18 POP_TOP
20 JUMP_BACKWARD 11 (to 6)
22 END_FOR
24 POP_TOP
26 RETURN_CONST 1 (None)
28 CALL_INTRINSIC_1 3 (INTRINSIC_STOPITERATION_ERROR)
30 RERAISE 1


0 NOP

2 LOAD_GLOBAL 0 (winreg)
4 LOAD_ATTR 2 (OpenKey)
6 PUSH_NULL
8 LOAD_FAST 0 (self)
10 LOAD_ATTR 4 (root)
12 LOAD_FAST 0 (self)
14 LOAD_ATTR 6 (base_path)
16 LOAD_CONST 1 (0)
18 LOAD_GLOBAL 0 (winreg)
20 LOAD_ATTR 8 (KEY_WRITE)
22 CALL 4
24 STORE_FAST 2 (key)

26 LOAD_GLOBAL 0 (winreg)
28 LOAD_ATTR 10 (DeleteValue)
30 PUSH_NULL
32 LOAD_FAST_LOAD_FAST 33 (key, name)
34 CALL 2
36 POP_TOP

38 LOAD_GLOBAL 0 (winreg)
40 LOAD_ATTR 12 (CloseKey)
42 PUSH_NULL
44 LOAD_FAST 2 (key)
46 CALL 1
48 POP_TOP
50 RETURN_CONST 2 (None)
52 PUSH_EXC_INFO

54 POP_TOP

56 POP_EXCEPT
58 RETURN_CONST 2 (None)
60 COPY 3
62 POP_EXCEPT
64 RERAISE 1


0 LOAD_GLOBAL 1 (NULL + RegistryManager)
2 CALL 0
4 STORE_DEREF 1 (reg)

6 LOAD_DEREF 1 (reg)
8 LOAD_ATTR 3 (NULL|self + get)
10 LOAD_CONST 1 ("r8")
12 CALL 1
14 LOAD_CONST 2 (".effie")
16 COMPARE_OP 88 (==)
18 POP_JUMP_IF_FALSE 65 (to 64)

20 LOAD_GLOBAL 5 (NULL + print)
22 CALL 0
24 POP_TOP

26 LOAD_GLOBAL 5 (NULL + print)
28 LOAD_CONST 3 ("You've done it, my man.")
30 CALL 1
32 POP_TOP

34 LOAD_GLOBAL 5 (NULL + print)
36 LOAD_CONST 4 ("The sun now glows a little brighter.")
38 CALL 1
40 POP_TOP

42 LOAD_GLOBAL 5 (NULL + print)
44 LOAD_CONST 5 ('"Thank you for playing."')
46 CALL 1
48 POP_TOP

50 LOAD_GLOBAL 5 (NULL + print)
52 CALL 0
54 POP_TOP

56 LOAD_GLOBAL 7 (NULL + destruction)
58 LOAD_DEREF 1 (reg)
60 LOAD_CONST 6 (False)
62 CALL 2
64 POP_TOP

66 LOAD_GLOBAL 9 (NULL + any)
68 LOAD_FAST 1 (reg)
70 BUILD_TUPLE 1
72 LOAD_CONST 7 (code object <genexpr>)
74 MAKE_FUNCTION
76 SET_FUNCTION_ATTRIBUTE 8
78 LOAD_GLOBAL 11 (NULL + range)
80 LOAD_CONST 8 (8)
82 CALL 1
84 GET_ITER
86 CALL 0
88 CALL 1
90 TO_BOOL
92 POP_JUMP_IF_FALSE 109 (to 170)

94 LOAD_GLOBAL 5 (NULL + print)
96 CALL 0
98 POP_TOP

100 LOAD_GLOBAL 5 (NULL + print)
102 LOAD_CONST 9 ("You return to the same room.")
104 CALL 1
106 POP_TOP

108 LOAD_GLOBAL 5 (NULL + print)
110 LOAD_CONST 10 ("Niko is still there. Waiting.")
112 CALL 1
114 POP_TOP

116 LOAD_GLOBAL 5 (NULL + print)
118 LOAD_CONST 11 ('"You failed last time. We\'re stuck in a loop now."')
120 CALL 1
122 POP_TOP

124 LOAD_GLOBAL 5 (NULL + print)
126 LOAD_CONST 12 ('"Like Sisyphus pushing the boulder. Like Bill Murray in Groundhog Day."')
128 CALL 1
130 POP_TOP

132 LOAD_GLOBAL 5 (NULL + print)
134 LOAD_CONST 13 ('"We\'re trapped here. Forever. Rolling the same rock up the same hill."')
136 CALL 1
138 POP_TOP

140 LOAD_GLOBAL 5 (NULL + print)
142 LOAD_CONST 14 ('"There\'s no way out anymore. You had one chance."')
144 CALL 1
146 POP_TOP

148 LOAD_GLOBAL 5 (NULL + print)
150 LOAD_CONST 15 ("[The program terminates. The loop is sealed.]")
152 CALL 1
154 POP_TOP

156 LOAD_GLOBAL 5 (NULL + print)
158 CALL 0
160 POP_TOP

162 LOAD_GLOBAL 7 (NULL + destruction)
164 LOAD_DEREF 1 (reg)
166 LOAD_CONST 6 (False)
168 CALL 2
170 POP_TOP

172 LOAD_GLOBAL 5 (NULL + print)
174 CALL 0
176 POP_TOP

178 LOAD_GLOBAL 5 (NULL + print)
180 LOAD_CONST 16 ("Niko is trapped in a puzzle.")
182 CALL 1
184 POP_TOP

186 LOAD_GLOBAL 5 (NULL + print)
188 LOAD_CONST 17 ("Scratches on the walls read:")
190 CALL 1
192 POP_TOP

194 LOAD_GLOBAL 5 (NULL + print)
196 CALL 0
198 POP_TOP

200 LOAD_GLOBAL 5 (NULL + print)
202 LOAD_CONST 18 ("   THIS IS YOUR ONLY CHANCE.   ")
204 CALL 1
206 POP_TOP

208 LOAD_GLOBAL 5 (NULL + print)
210 LOAD_CONST 19 ("ONE SHOT, OR STUCK HERE TRYING,")
212 CALL 1
214 POP_TOP

216 LOAD_GLOBAL 5 (NULL + print)
218 LOAD_CONST 20 ("            FOREVER.           ")
220 CALL 1
222 POP_TOP

224 LOAD_GLOBAL 5 (NULL + print)
226 CALL 0
228 POP_TOP

230 LOAD_GLOBAL 5 (NULL + print)
232 LOAD_CONST 21 ('"Please... you have to help me. I don\'t understand this."')
234 CALL 1
236 POP_TOP

238 LOAD_GLOBAL 5 (NULL + print)
240 LOAD_CONST 22 ("Niko looks at you with desperate hope.")
242 CALL 1
244 POP_TOP

246 LOAD_GLOBAL 5 (NULL + print)
248 CALL 0
250 POP_TOP

252 NOP

254 LOAD_DEREF 1 (reg)
256 LOAD_ATTR 13 (NULL|self + set)
258 LOAD_CONST 23 ("r0")
260 LOAD_GLOBAL 15 (NULL + input)
262 LOAD_CONST 24 ('"Do you know the way out?"\n> ')
264 CALL 1
266 LOAD_ATTR 17 (NULL|self + strip)
268 CALL 0
270 LOAD_ATTR 19 (NULL|self + encode)
272 CALL 0
274 CALL 2
276 POP_TOP

278 LOAD_GLOBAL 21 (NULL + len)
280 LOAD_DEREF 1 (reg)
282 LOAD_ATTR 3 (NULL|self + get)
284 LOAD_CONST 23 ("r0")
286 CALL 1
288 CALL 1
290 LOAD_CONST 25 (162)
292 COMPARE_OP 119 (!=)
294 POP_JUMP_IF_FALSE 11 (to 302)

296 LOAD_GLOBAL 7 (NULL + destruction)
298 LOAD_DEREF 1 (reg)
300 CALL 1
302 POP_TOP

304 LOAD_DEREF 1 (reg)
306 LOAD_ATTR 13 (NULL|self + set)
308 LOAD_CONST 26 ("r1")
310 LOAD_GLOBAL 11 (NULL + range)
312 LOAD_CONST 27 (6)
314 CALL 1
316 GET_ITER
318 LOAD_FAST_AND_CLEAR 0 (i)
320 SWAP 2
322 BUILD_LIST 0
324 SWAP 2
326 GET_ITER
328 FOR_ITER 32 (to 362)
330 STORE_FAST 0 (i)
332 LOAD_DEREF 1 (reg)
334 LOAD_ATTR 3 (NULL|self + get)
336 LOAD_CONST 23 ("r0")
338 CALL 1
340 LOAD_FAST 0 (i)
342 LOAD_CONST 28 (27)
344 BINARY_OP 5 (*)
346 LOAD_FAST 0 (i)
348 LOAD_CONST 29 (1)
350 BINARY_OP 0 (+)
352 LOAD_CONST 28 (27)
354 BINARY_OP 5 (*)
356 BINARY_SLICE
358 LIST_APPEND 2
360 JUMP_BACKWARD 34 (to 326)
362 END_FOR
364 POP_TOP
366 SWAP 2
368 STORE_FAST 0 (i)
370 CALL 2
372 POP_TOP

374 LOAD_DEREF 1 (reg)
376 LOAD_ATTR 13 (NULL|self + set)
378 LOAD_CONST 23 ("r0")
380 LOAD_CONST 30 (0)
382 CALL 2
384 POP_TOP

386 NOP

388 LOAD_DEREF 1 (reg)
390 LOAD_ATTR 3 (NULL|self + get)
392 LOAD_CONST 23 ("r0")
394 CALL 1
396 LOAD_CONST 30 (0)
398 COMPARE_OP 88 (==)
400 POP_JUMP_IF_FALSE 567 (to 752)

402 LOAD_DEREF 1 (reg)
404 LOAD_ATTR 13 (NULL|self + set)
406 LOAD_CONST 31 ("r3")
408 BUILD_LIST 0
410 LOAD_CONST 32 ((121, 105, 121, 122, 103, 98, 70, 112, 41, 112, 102, 40, 105, 44, 112, 127, 47, 42, 112, 46, 105, 117, 112, 125, 46, 123, 41))
412 LIST_EXTEND 1
414 CALL 2
416 POP_TOP

418 LOAD_DEREF 1 (reg)
420 LOAD_ATTR 13 (NULL|self + set)
422 LOAD_CONST 33 ("r2")
424 LOAD_CONST 30 (0)
426 CALL 2
428 POP_TOP

430 LOAD_DEREF 1 (reg)
432 LOAD_ATTR 3 (NULL|self + get)
434 LOAD_CONST 33 ("r2")
436 CALL 1
438 LOAD_CONST 28 (27)
440 COMPARE_OP 18 (<)
442 POP_JUMP_IF_FALSE 469 (to 730)

444 LOAD_DEREF 1 (reg)
446 LOAD_ATTR 13 (NULL|self + set)

448 LOAD_CONST 26 ("r1")
450 LOAD_DEREF 1 (reg)
452 LOAD_ATTR 3 (NULL|self + get)
454 LOAD_CONST 26 ("r1")
456 CALL 1
458 LOAD_CONST 0 (None)
460 LOAD_DEREF 1 (reg)
462 LOAD_ATTR 3 (NULL|self + get)
464 LOAD_CONST 23 ("r0")
466 CALL 1
468 BINARY_SLICE

470 LOAD_DEREF 1 (reg)
472 LOAD_ATTR 3 (NULL|self + get)
474 LOAD_CONST 26 ("r1")
476 CALL 1
478 LOAD_DEREF 1 (reg)
480 LOAD_ATTR 3 (NULL|self + get)
482 LOAD_CONST 23 ("r0")
484 CALL 1
486 BINARY_SUBSCR
488 LOAD_CONST 0 (None)
490 LOAD_DEREF 1 (reg)
492 LOAD_ATTR 3 (NULL|self + get)
494 LOAD_CONST 33 ("r2")
496 CALL 1
498 BINARY_SLICE

500 LOAD_GLOBAL 25 (NULL + bytes)
502 LOAD_DEREF 1 (reg)
504 LOAD_ATTR 3 (NULL|self + get)
506 LOAD_CONST 26 ("r1")
508 CALL 1
510 LOAD_DEREF 1 (reg)
512 LOAD_ATTR 3 (NULL|self + get)
514 LOAD_CONST 23 ("r0")
516 CALL 1
518 BINARY_SUBSCR
520 LOAD_DEREF 1 (reg)
522 LOAD_ATTR 3 (NULL|self + get)
524 LOAD_CONST 33 ("r2")
526 CALL 1
528 BINARY_SUBSCR
530 LOAD_DEREF 1 (reg)
532 LOAD_ATTR 3 (NULL|self + get)
534 LOAD_CONST 26 ("r1")
536 CALL 1
538 LOAD_DEREF 1 (reg)
540 LOAD_ATTR 3 (NULL|self + get)
542 LOAD_CONST 23 ("r0")
544 CALL 1
546 BINARY_SUBSCR
548 LOAD_DEREF 1 (reg)
550 LOAD_ATTR 3 (NULL|self + get)
552 LOAD_CONST 33 ("r2")
554 CALL 1
556 BINARY_SUBSCR
558 LOAD_CONST 29 (1)
560 BINARY_OP 9 (>>)
562 BINARY_OP 12 (^)
564 BUILD_LIST 1
566 CALL 1

568 BINARY_OP 0 (+)

570 LOAD_DEREF 1 (reg)
572 LOAD_ATTR 3 (NULL|self + get)
574 LOAD_CONST 26 ("r1")
576 CALL 1
578 LOAD_DEREF 1 (reg)
580 LOAD_ATTR 3 (NULL|self + get)
582 LOAD_CONST 23 ("r0")
584 CALL 1
586 BINARY_SUBSCR
588 LOAD_DEREF 1 (reg)
590 LOAD_ATTR 3 (NULL|self + get)
592 LOAD_CONST 33 ("r2")
594 CALL 1
596 LOAD_CONST 29 (1)
598 BINARY_OP 0 (+)
600 LOAD_CONST 0 (None)
602 BINARY_SLICE

604 BINARY_OP 0 (+)

606 BUILD_LIST 1
608 BINARY_OP 0 (+)

610 LOAD_DEREF 1 (reg)
612 LOAD_ATTR 3 (NULL|self + get)
614 LOAD_CONST 26 ("r1")
616 CALL 1
618 LOAD_DEREF 1 (reg)
620 LOAD_ATTR 3 (NULL|self + get)
622 LOAD_CONST 23 ("r0")
624 CALL 1
626 LOAD_CONST 29 (1)
628 BINARY_OP 0 (+)
630 LOAD_CONST 0 (None)
632 BINARY_SLICE

634 BINARY_OP 0 (+)

636 CALL 2
638 POP_TOP

640 LOAD_DEREF 1 (reg)
642 LOAD_ATTR 3 (NULL|self + get)
644 LOAD_CONST 26 ("r1")
646 CALL 1
648 LOAD_CONST 30 (0)
650 BINARY_SUBSCR
652 LOAD_DEREF 1 (reg)
654 LOAD_ATTR 3 (NULL|self + get)
656 LOAD_CONST 33 ("r2")
658 CALL 1
660 BINARY_SUBSCR
662 LOAD_DEREF 1 (reg)
664 LOAD_ATTR 3 (NULL|self + get)
666 LOAD_CONST 31 ("r3")
668 CALL 1
670 LOAD_DEREF 1 (reg)
672 LOAD_ATTR 3 (NULL|self + get)
674 LOAD_CONST 33 ("r2")
676 CALL 1
678 BINARY_SUBSCR
680 COMPARE_OP 119 (!=)
682 POP_JUMP_IF_FALSE 11 (to 690)

684 LOAD_GLOBAL 7 (NULL + destruction)
686 LOAD_DEREF 1 (reg)
688 CALL 1
690 POP_TOP

692 LOAD_DEREF 1 (reg)
694 LOAD_ATTR 13 (NULL|self + set)
696 LOAD_CONST 33 ("r2")
698 LOAD_DEREF 1 (reg)
700 LOAD_ATTR 3 (NULL|self + get)
702 LOAD_CONST 33 ("r2")
704 CALL 1
706 LOAD_CONST 29 (1)
708 BINARY_OP 0 (+)
710 CALL 2
712 POP_TOP

714 LOAD_DEREF 1 (reg)
716 LOAD_ATTR 3 (NULL|self + get)
718 LOAD_CONST 33 ("r2")
720 CALL 1
722 LOAD_CONST 28 (27)
724 COMPARE_OP 18 (<)
726 POP_JUMP_IF_FALSE 3 (to 730)
728 JUMP_BACKWARD 469 (to 444)

730 LOAD_DEREF 1 (reg)
732 LOAD_ATTR 13 (NULL|self + set)
734 LOAD_CONST 23 ("r0")
736 LOAD_DEREF 1 (reg)
738 LOAD_ATTR 3 (NULL|self + get)
740 LOAD_CONST 23 ("r0")
742 CALL 1
744 LOAD_CONST 29 (1)
746 BINARY_OP 0 (+)
748 CALL 2
750 POP_TOP
752 JUMP_FORWARD 5671 (to 5010)

754 LOAD_DEREF 1 (reg)
756 LOAD_ATTR 3 (NULL|self + get)
758 LOAD_CONST 23 ("r0")
760 CALL 1
762 LOAD_CONST 29 (1)
764 COMPARE_OP 88 (==)
766 POP_JUMP_IF_FALSE 626 (to 1158)

768 LOAD_DEREF 1 (reg)
770 LOAD_ATTR 13 (NULL|self + set)
772 LOAD_CONST 34 ("r4")
774 BUILD_LIST 0
776 LOAD_CONST 35 ((59, 60, 82, 46, 58, 91, 53, 75, 98, 75, 91, 94, 54, 67, 82, 50, 79, 57, 51, 47, 92, 91, 68, 56, 77, 57, 80))
778 LIST_EXTEND 1
780 CALL 2
782 POP_TOP

784 LOAD_DEREF 1 (reg)
786 LOAD_ATTR 13 (NULL|self + set)
788 LOAD_CONST 33 ("r2")
790 LOAD_CONST 30 (0)
792 CALL 2
794 POP_TOP

796 LOAD_DEREF 1 (reg)
798 LOAD_ATTR 3 (NULL|self + get)
800 LOAD_CONST 33 ("r2")
802 CALL 1
804 LOAD_CONST 28 (27)
806 COMPARE_OP 18 (<)
808 POP_JUMP_IF_FALSE 528 (to 1136)

810 LOAD_DEREF 1 (reg)
812 LOAD_ATTR 13 (NULL|self + set)
814 LOAD_CONST 31 ("r3")
816 LOAD_DEREF 1 (reg)
818 LOAD_ATTR 3 (NULL|self + get)
820 LOAD_CONST 33 ("r2")
822 CALL 1
824 LOAD_CONST 36 (13)
826 BINARY_OP 10 (-)
828 LOAD_CONST 37 (2)
830 BINARY_OP 2 (//)
832 LOAD_DEREF 1 (reg)
834 LOAD_ATTR 3 (NULL|self + get)
836 LOAD_CONST 33 ("r2")
838 CALL 1
840 LOAD_CONST 29 (1)
842 BINARY_OP 1 (&)
844 LOAD_CONST 30 (0)
846 COMPARE_OP 88 (==)
848 POP_JUMP_IF_FALSE 2 (to 852)
850 LOAD_CONST 38 (-1)
852 JUMP_FORWARD 1 (to 856)
854 LOAD_CONST 29 (1)
856 BINARY_OP 5 (*)
858 CALL 2
860 POP_TOP

862 LOAD_DEREF 1 (reg)
864 LOAD_ATTR 13 (NULL|self + set)

866 LOAD_CONST 26 ("r1")
868 LOAD_DEREF 1 (reg)
870 LOAD_ATTR 3 (NULL|self + get)
872 LOAD_CONST 26 ("r1")
874 CALL 1
876 LOAD_CONST 0 (None)
878 LOAD_DEREF 1 (reg)
880 LOAD_ATTR 3 (NULL|self + get)
882 LOAD_CONST 23 ("r0")
884 CALL 1
886 BINARY_SLICE

888 LOAD_DEREF 1 (reg)
890 LOAD_ATTR 3 (NULL|self + get)
892 LOAD_CONST 26 ("r1")
894 CALL 1
896 LOAD_DEREF 1 (reg)
898 LOAD_ATTR 3 (NULL|self + get)
900 LOAD_CONST 23 ("r0")
902 CALL 1
904 BINARY_SUBSCR
906 LOAD_CONST 0 (None)
908 LOAD_DEREF 1 (reg)
910 LOAD_ATTR 3 (NULL|self + get)
912 LOAD_CONST 33 ("r2")
914 CALL 1
916 BINARY_SLICE

918 LOAD_GLOBAL 25 (NULL + bytes)
920 LOAD_DEREF 1 (reg)
922 LOAD_ATTR 3 (NULL|self + get)
924 LOAD_CONST 26 ("r1")
926 CALL 1
928 LOAD_DEREF 1 (reg)
930 LOAD_ATTR 3 (NULL|self + get)
932 LOAD_CONST 23 ("r0")
934 CALL 1
936 BINARY_SUBSCR
938 LOAD_DEREF 1 (reg)
940 LOAD_ATTR 3 (NULL|self + get)
942 LOAD_CONST 33 ("r2")
944 CALL 1
946 BINARY_SUBSCR
948 LOAD_DEREF 1 (reg)
950 LOAD_ATTR 27 (NULL|self + u2s)
952 LOAD_DEREF 1 (reg)
954 LOAD_ATTR 3 (NULL|self + get)
956 LOAD_CONST 31 ("r3")
958 CALL 1
960 CALL 1
962 BINARY_OP 0 (+)
964 BUILD_LIST 1
966 CALL 1

968 BINARY_OP 0 (+)

970 LOAD_DEREF 1 (reg)
972 LOAD_ATTR 3 (NULL|self + get)
974 LOAD_CONST 26 ("r1")
976 CALL 1
978 LOAD_DEREF 1 (reg)
980 LOAD_ATTR 3 (NULL|self + get)
982 LOAD_CONST 23 ("r0")
984 CALL 1
986 BINARY_SUBSCR
988 LOAD_DEREF 1 (reg)
990 LOAD_ATTR 3 (NULL|self + get)
992 LOAD_CONST 33 ("r2")
994 CALL 1
996 LOAD_CONST 29 (1)
998 BINARY_OP 0 (+)
1000 LOAD_CONST 0 (None)
1002 BINARY_SLICE

1004 BINARY_OP 0 (+)

1006 BUILD_LIST 1
1008 BINARY_OP 0 (+)

1010 LOAD_DEREF 1 (reg)
1012 LOAD_ATTR 3 (NULL|self + get)
1014 LOAD_CONST 26 ("r1")
1016 CALL 1
1018 LOAD_DEREF 1 (reg)
1020 LOAD_ATTR 3 (NULL|self + get)
1022 LOAD_CONST 23 ("r0")
1024 CALL 1
1026 LOAD_CONST 29 (1)
1028 BINARY_OP 0 (+)
1030 LOAD_CONST 0 (None)
1032 BINARY_SLICE

1034 BINARY_OP 0 (+)

1036 CALL 2
1038 POP_TOP

1040 LOAD_DEREF 1 (reg)
1042 LOAD_ATTR 3 (NULL|self + get)
1044 LOAD_CONST 26 ("r1")
1046 CALL 1
1048 LOAD_DEREF 1 (reg)
1050 LOAD_ATTR 3 (NULL|self + get)
1052 LOAD_CONST 23 ("r0")
1054 CALL 1
1056 BINARY_SUBSCR
1058 LOAD_DEREF 1 (reg)
1060 LOAD_ATTR 3 (NULL|self + get)
1062 LOAD_CONST 33 ("r2")
1064 CALL 1
1066 BINARY_SUBSCR
1068 LOAD_DEREF 1 (reg)
1070 LOAD_ATTR 3 (NULL|self + get)
1072 LOAD_CONST 34 ("r4")
1074 CALL 1
1076 LOAD_DEREF 1 (reg)
1078 LOAD_ATTR 3 (NULL|self + get)
1080 LOAD_CONST 33 ("r2")
1082 CALL 1
1084 BINARY_SUBSCR
1086 COMPARE_OP 119 (!=)
1088 POP_JUMP_IF_FALSE 11 (to 1096)

1090 LOAD_GLOBAL 7 (NULL + destruction)
1092 LOAD_DEREF 1 (reg)
1094 CALL 1
1096 POP_TOP

1098 LOAD_DEREF 1 (reg)
1100 LOAD_ATTR 13 (NULL|self + set)
1102 LOAD_CONST 33 ("r2")
1104 LOAD_DEREF 1 (reg)
1106 LOAD_ATTR 3 (NULL|self + get)
1108 LOAD_CONST 33 ("r2")
1110 CALL 1
1112 LOAD_CONST 29 (1)
1114 BINARY_OP 0 (+)
1116 CALL 2
1118 POP_TOP

1120 LOAD_DEREF 1 (reg)
1122 LOAD_ATTR 3 (NULL|self + get)
1124 LOAD_CONST 33 ("r2")
1126 CALL 1
1128 LOAD_CONST 28 (27)
1130 COMPARE_OP 18 (<)
1132 POP_JUMP_IF_FALSE 3 (to 1136)
1134 JUMP_BACKWARD 528 (to 810)

1136 LOAD_DEREF 1 (reg)
1138 LOAD_ATTR 13 (NULL|self + set)
1140 LOAD_CONST 23 ("r0")
1142 LOAD_DEREF 1 (reg)
1144 LOAD_ATTR 3 (NULL|self + get)
1146 LOAD_CONST 23 ("r0")
1148 CALL 1
1150 LOAD_CONST 29 (1)
1152 BINARY_OP 0 (+)
1154 CALL 2
1156 POP_TOP
1158 JUMP_FORWARD 5023 (to 5010)

1160 LOAD_DEREF 1 (reg)
1162 LOAD_ATTR 3 (NULL|self + get)
1164 LOAD_CONST 23 ("r0")
1166 CALL 1
1168 LOAD_CONST 37 (2)
1170 COMPARE_OP 88 (==)
1172 POP_JUMP_IF_FALSE 530 (to 1482)

1174 LOAD_DEREF 1 (reg)
1176 LOAD_ATTR 13 (NULL|self + set)
1178 LOAD_CONST 34 ("r4")
1180 BUILD_LIST 0
1182 LOAD_CONST 39 ((63, 43, 39, 12, 19, 36, 61, 6, 34, 50, 63, 61, 54, 53, 24, 37, 59, 44, 46, 66, 55, 57, 13, 59, 41, 11, 13, 15, 53, 23, 51, 22, 64, 0, 32))
1184 LIST_EXTEND 1
1186 CALL 2
1188 POP_TOP

1190 LOAD_DEREF 1 (reg)
1192 LOAD_ATTR 13 (NULL|self + set)
1194 LOAD_CONST 31 ("r3")
1196 LOAD_GLOBAL 28 (int)
1198 LOAD_ATTR 31 (NULL|self + from_bytes)
1200 LOAD_DEREF 1 (reg)
1202 LOAD_ATTR 3 (NULL|self + get)
1204 LOAD_CONST 26 ("r1")
1206 CALL 1
1208 LOAD_DEREF 1 (reg)
1210 LOAD_ATTR 3 (NULL|self + get)
1212 LOAD_CONST 23 ("r0")
1214 CALL 1
1216 BINARY_SUBSCR
1218 CALL 1
1220 CALL 2
1222 POP_TOP

1224 LOAD_DEREF 1 (reg)
1226 LOAD_ATTR 13 (NULL|self + set)
1228 LOAD_CONST 33 ("r2")
1230 LOAD_CONST 30 (0)
1232 CALL 2
1234 POP_TOP

1236 LOAD_DEREF 1 (reg)
1238 LOAD_ATTR 3 (NULL|self + get)
1240 LOAD_CONST 33 ("r2")
1242 CALL 1
1244 LOAD_GLOBAL 21 (NULL + len)
1246 LOAD_DEREF 1 (reg)
1248 LOAD_ATTR 3 (NULL|self + get)
1250 LOAD_CONST 34 ("r4")
1252 CALL 1
1254 CALL 1
1256 COMPARE_OP 18 (<)
1258 POP_JUMP_IF_FALSE 338 (to 1460)

1260 LOAD_DEREF 1 (reg)
1262 LOAD_ATTR 13 (NULL|self + set)
1264 LOAD_CONST 40 ("r5")
1266 LOAD_DEREF 1 (reg)
1268 LOAD_ATTR 3 (NULL|self + get)
1270 LOAD_CONST 31 ("r3")
1272 CALL 1
1274 LOAD_CONST 41 (69)
1276 LOAD_GLOBAL 21 (NULL + len)
1278 LOAD_DEREF 1 (reg)
1280 LOAD_ATTR 3 (NULL|self + get)
1282 LOAD_CONST 34 ("r4")
1284 CALL 1
1286 CALL 1
1288 LOAD_CONST 29 (1)
1290 BINARY_OP 10 (-)
1292 LOAD_DEREF 1 (reg)
1294 LOAD_ATTR 3 (NULL|self + get)
1296 LOAD_CONST 33 ("r2")
1298 CALL 1
1300 BINARY_OP 10 (-)
1302 BINARY_OP 8 (**)
1304 BINARY_OP 2 (//)
1306 LOAD_CONST 41 (69)
1308 BINARY_OP 6 (%)
1310 CALL 2
1312 POP_TOP

1314 LOAD_DEREF 1 (reg)
1316 LOAD_ATTR 13 (NULL|self + set)
1318 LOAD_CONST 31 ("r3")
1320 LOAD_DEREF 1 (reg)
1322 LOAD_ATTR 3 (NULL|self + get)
1324 LOAD_CONST 31 ("r3")
1326 CALL 1
1328 LOAD_DEREF 1 (reg)
1330 LOAD_ATTR 3 (NULL|self + get)
1332 LOAD_CONST 40 ("r5")
1334 CALL 1
1336 LOAD_CONST 41 (69)
1338 LOAD_GLOBAL 21 (NULL + len)
1340 LOAD_DEREF 1 (reg)
1342 LOAD_ATTR 3 (NULL|self + get)
1344 LOAD_CONST 34 ("r4")
1346 CALL 1
1348 CALL 1
1350 LOAD_CONST 29 (1)
1352 BINARY_OP 10 (-)
1354 LOAD_DEREF 1 (reg)
1356 LOAD_ATTR 3 (NULL|self + get)
1358 LOAD_CONST 33 ("r2")
1360 CALL 1
1362 BINARY_OP 10 (-)
1364 BINARY_OP 8 (**)
1366 BINARY_OP 5 (*)
1368 BINARY_OP 10 (-)
1370 CALL 2
1372 POP_TOP

1374 LOAD_DEREF 1 (reg)
1376 LOAD_ATTR 3 (NULL|self + get)
1378 LOAD_CONST 40 ("r5")
1380 CALL 1
1382 LOAD_DEREF 1 (reg)
1384 LOAD_ATTR 3 (NULL|self + get)
1386 LOAD_CONST 34 ("r4")
1388 CALL 1
1390 LOAD_DEREF 1 (reg)
1392 LOAD_ATTR 3 (NULL|self + get)
1394 LOAD_CONST 33 ("r2")
1396 CALL 1
1398 BINARY_SUBSCR
1400 COMPARE_OP 119 (!=)
1402 POP_JUMP_IF_FALSE 11 (to 1410)

1404 LOAD_GLOBAL 7 (NULL + destruction)
1406 LOAD_DEREF 1 (reg)
1408 CALL 1
1410 POP_TOP

1412 LOAD_DEREF 1 (reg)
1414 LOAD_ATTR 13 (NULL|self + set)
1416 LOAD_CONST 33 ("r2")
1418 LOAD_DEREF 1 (reg)
1420 LOAD_ATTR 3 (NULL|self + get)
1422 LOAD_CONST 33 ("r2")
1424 CALL 1
1426 LOAD_CONST 29 (1)
1428 BINARY_OP 0 (+)
1430 CALL 2
1432 POP_TOP

1434 LOAD_DEREF 1 (reg)
1436 LOAD_ATTR 3 (NULL|self + get)
1438 LOAD_CONST 33 ("r2")
1440 CALL 1
1442 LOAD_GLOBAL 21 (NULL + len)
1444 LOAD_DEREF 1 (reg)
1446 LOAD_ATTR 3 (NULL|self + get)
1448 LOAD_CONST 34 ("r4")
1450 CALL 1
1452 CALL 1
1454 COMPARE_OP 18 (<)
1456 POP_JUMP_IF_FALSE 3 (to 1460)
1458 JUMP_BACKWARD 338 (to 1260)

1460 LOAD_DEREF 1 (reg)
1462 LOAD_ATTR 13 (NULL|self + set)
1464 LOAD_CONST 23 ("r0")
1466 LOAD_DEREF 1 (reg)
1468 LOAD_ATTR 3 (NULL|self + get)
1470 LOAD_CONST 23 ("r0")
1472 CALL 1
1474 LOAD_CONST 29 (1)
1476 BINARY_OP 0 (+)
1478 CALL 2
1480 POP_TOP
1482 JUMP_FORWARD 4471 (to 5010)

1484 LOAD_DEREF 1 (reg)
1486 LOAD_ATTR 3 (NULL|self + get)
1488 LOAD_CONST 23 ("r0")
1490 CALL 1
1492 LOAD_CONST 42 (3)
1494 COMPARE_OP 88 (==)
1496 POP_JUMP_IF_FALSE 313 (to 1694)

1498 LOAD_DEREF 1 (reg)
1500 LOAD_ATTR 13 (NULL|self + set)
1502 LOAD_CONST 34 ("r4")
1504 LOAD_CONST 43 ('\n========================\n  THE E†IGMA OF HEAVEN\n========================\n\nPRAISE THE LORD! The air conditioner †eeps them away it sings gospels and\n†RAISE THE LORD! Finding faith in wh†te noise.\nPRAISE THE LORD! The messages are coming in loud and clear †nd\nI hear them and I see them in t†e sky the towers are sending messages and\nI hear them and I see them.\nPRAISE T†E LORD! The people in the parkin† lot can\'t hurt me anymore\nthey can\'t †urt me anymore their words are weak and the lord is strong.\nPRAISE THE LORD! T†e bible shows the way and the way prot†cts me and\nI\'ve seen the messag†s and I heart them and I see them and they can\'t\nhurt me anymore.\nPRAISE THE L†RD!\n\nCHAPTERS:                        †        ╔═══════════════╗\n—————————                    †            ║               ║\nI. T†e Enigma of Heaven:                  ║    HEAVEN     ║\n 9,999,999 Channels, Fi†ding Faith        ╟───────────────╢\n in White Noise... The God St†mulation!   ║               ║\nII. †he Hierarchy of Equality:            †   RADIATION   ║\n Angelic Voices†Echo Through the Halls    ╟─────────†─────╢\n of Heaven, Under the Railroad †ridge     ║               ║    "And I have\nIII. The Paradox of Fa†th:                ║     RADIO     ║      told you\n There\'s a Knocking a† the Door!          ╟──────†────────╢     the TRUTH,\n God is in, God is in!                    ║          †    ║\nIV. The Senselessness of Endlessness:     ║  TELEVISION   ║      for you\n Returning to an Empty Apartment          ║               ║   are my child,\n with a Grocery Store Guardian Angel      ╚═══════════════╝    and you have\n                                                              seen my face"\n\nAn EP titled "The Enigma of Heaven and Other Daily Delusions" ')
1506 CALL 2
1508 POP_TOP

1510 LOAD_DEREF 1 (reg)
1512 LOAD_ATTR 13 (NULL|self + set)
1514 LOAD_CONST 33 ("r2")
1516 LOAD_CONST 30 (0)
1518 CALL 2
1520 POP_TOP

1522 LOAD_DEREF 1 (reg)
1524 LOAD_ATTR 13 (NULL|self + set)
1526 LOAD_CONST 31 ("r3")
1528 LOAD_CONST 30 (0)
1530 CALL 2
1532 POP_TOP

1534 LOAD_DEREF 1 (reg)
1536 LOAD_ATTR 3 (NULL|self + get)
1538 LOAD_CONST 33 ("r2")
1540 CALL 1
1542 LOAD_CONST 28 (27)
1544 COMPARE_OP 18 (<)
1546 POP_JUMP_IF_FALSE 200 (to 1672)

1548 LOAD_DEREF 1 (reg)
1550 LOAD_ATTR 13 (NULL|self + set)
1552 LOAD_CONST 31 ("r3")
1554 LOAD_DEREF 1 (reg)
1556 LOAD_ATTR 3 (NULL|self + get)
1558 LOAD_CONST 31 ("r3")
1560 CALL 1
1562 LOAD_DEREF 1 (reg)
1564 LOAD_ATTR 3 (NULL|self + get)
1566 LOAD_CONST 26 ("r1")
1568 CALL 1
1570 LOAD_DEREF 1 (reg)
1572 LOAD_ATTR 3 (NULL|self + get)
1574 LOAD_CONST 23 ("r0")
1576 CALL 1
1578 BINARY_SUBSCR
1580 LOAD_DEREF 1 (reg)
1582 LOAD_ATTR 3 (NULL|self + get)
1584 LOAD_CONST 33 ("r2")
1586 CALL 1
1588 BINARY_SUBSCR
1590 BINARY_OP 0 (+)
1592 LOAD_CONST 44 (16)
1594 BINARY_OP 10 (-)
1596 CALL 2
1598 POP_TOP

1600 NOP

1602 LOAD_DEREF 1 (reg)
1604 LOAD_ATTR 3 (NULL|self + get)
1606 LOAD_CONST 34 ("r4")
1608 CALL 1
1610 LOAD_DEREF 1 (reg)
1612 LOAD_ATTR 3 (NULL|self + get)
1614 LOAD_CONST 31 ("r3")
1616 CALL 1
1618 BINARY_SUBSCR
1620 LOAD_CONST 45 ("†")
1622 COMPARE_OP 119 (!=)
1624 POP_JUMP_IF_FALSE 11 (to 1632)

1626 LOAD_GLOBAL 7 (NULL + destruction)
1628 LOAD_DEREF 1 (reg)
1630 CALL 1
1632 POP_TOP

1634 LOAD_DEREF 1 (reg)
1636 LOAD_ATTR 13 (NULL|self + set)
1638 LOAD_CONST 33 ("r2")
1640 LOAD_DEREF 1 (reg)
1642 LOAD_ATTR 3 (NULL|self + get)
1644 LOAD_CONST 33 ("r2")
1646 CALL 1
1648 LOAD_CONST 29 (1)
1650 BINARY_OP 0 (+)
1652 CALL 2
1654 POP_TOP

1656 LOAD_DEREF 1 (reg)
1658 LOAD_ATTR 3 (NULL|self + get)
1660 LOAD_CONST 33 ("r2")
1662 CALL 1
1664 LOAD_CONST 28 (27)
1666 COMPARE_OP 18 (<)
1668 POP_JUMP_IF_FALSE 2 (to 1672)
1670 JUMP_BACKWARD 200 (to 1548)

1672 LOAD_DEREF 1 (reg)
1674 LOAD_ATTR 13 (NULL|self + set)
1676 LOAD_CONST 23 ("r0")
1678 LOAD_DEREF 1 (reg)
1680 LOAD_ATTR 3 (NULL|self + get)
1682 LOAD_CONST 23 ("r0")
1684 CALL 1
1686 LOAD_CONST 29 (1)
1688 BINARY_OP 0 (+)
1690 CALL 2
1692 POP_TOP
1694 JUMP_FORWARD 4136 (to 5010)

1696 LOAD_DEREF 1 (reg)
1698 LOAD_ATTR 3 (NULL|self + get)
1700 LOAD_CONST 23 ("r0")
1702 CALL 1
1704 LOAD_CONST 46 (4)
1706 COMPARE_OP 88 (==)
1708 POP_JUMP_IF_FALSE 1360 (to 2598)

1710 LOAD_DEREF 1 (reg)
1712 LOAD_ATTR 13 (NULL|self + set)
1714 LOAD_CONST 34 ("r4")
1716 BUILD_LIST 0
1718 LOAD_CONST 47 ((1773468, 985071, 984495, 984751, 984959, 853983, 1509663, 1511295, 1510271))
1720 LIST_EXTEND 1
1722 CALL 2
1724 POP_TOP

1726 LOAD_DEREF 1 (reg)
1728 LOAD_ATTR 13 (NULL|self + set)
1730 LOAD_CONST 33 ("r2")
1732 LOAD_CONST 30 (0)
1734 CALL 2
1736 POP_TOP

1738 LOAD_DEREF 1 (reg)
1740 LOAD_ATTR 3 (NULL|self + get)
1742 LOAD_CONST 33 ("r2")
1744 CALL 1
1746 LOAD_CONST 48 (9)
1748 COMPARE_OP 18 (<)
1750 POP_JUMP_IF_FALSE 1262 (to 2576)

1752 LOAD_DEREF 1 (reg)
1754 LOAD_ATTR 13 (NULL|self + set)

1756 LOAD_CONST 40 ("r5")
1758 LOAD_DEREF 1 (reg)
1760 LOAD_ATTR 3 (NULL|self + get)
1762 LOAD_CONST 26 ("r1")
1764 CALL 1
1766 LOAD_DEREF 1 (reg)
1768 LOAD_ATTR 3 (NULL|self + get)
1770 LOAD_CONST 23 ("r0")
1772 CALL 1
1774 BINARY_SUBSCR
1776 LOAD_DEREF 1 (reg)
1778 LOAD_ATTR 3 (NULL|self + get)
1780 LOAD_CONST 33 ("r2")
1782 CALL 1
1784 LOAD_CONST 42 (3)
1786 BINARY_OP 5 (*)
1788 BINARY_SUBSCR
1790 LOAD_DEREF 1 (reg)
1792 LOAD_ATTR 3 (NULL|self + get)
1794 LOAD_CONST 26 ("r1")
1796 CALL 1
1798 LOAD_DEREF 1 (reg)
1800 LOAD_ATTR 3 (NULL|self + get)
1802 LOAD_CONST 23 ("r0")
1804 CALL 1
1806 BINARY_SUBSCR
1808 LOAD_DEREF 1 (reg)
1810 LOAD_ATTR 3 (NULL|self + get)
1812 LOAD_CONST 33 ("r2")
1814 CALL 1
1816 LOAD_CONST 42 (3)
1818 BINARY_OP 5 (*)
1820 BINARY_SUBSCR
1822 LOAD_CONST 49 (12)
1824 BINARY_OP 3 (<<)
1826 BINARY_OP 7 (|)
1828 LOAD_CONST 50 (983055)
1830 BINARY_OP 1 (&)
1832 LOAD_DEREF 1 (reg)
1834 LOAD_ATTR 3 (NULL|self + get)
1836 LOAD_CONST 26 ("r1")
1838 CALL 1
1840 LOAD_DEREF 1 (reg)
1842 LOAD_ATTR 3 (NULL|self + get)
1844 LOAD_CONST 23 ("r0")
1846 CALL 1
1848 BINARY_SUBSCR
1850 LOAD_DEREF 1 (reg)
1852 LOAD_ATTR 3 (NULL|self + get)
1854 LOAD_CONST 33 ("r2")
1856 CALL 1
1858 LOAD_CONST 42 (3)
1860 BINARY_OP 5 (*)
1862 BINARY_SUBSCR
1864 LOAD_DEREF 1 (reg)
1866 LOAD_ATTR 3 (NULL|self + get)
1868 LOAD_CONST 26 ("r1")
1870 CALL 1
1872 LOAD_DEREF 1 (reg)
1874 LOAD_ATTR 3 (NULL|self + get)
1876 LOAD_CONST 23 ("r0")
1878 CALL 1
1880 BINARY_SUBSCR
1882 LOAD_DEREF 1 (reg)
1884 LOAD_ATTR 3 (NULL|self + get)
1886 LOAD_CONST 33 ("r2")
1888 CALL 1
1890 LOAD_CONST 42 (3)
1892 BINARY_OP 5 (*)
1894 BINARY_SUBSCR
1896 LOAD_CONST 27 (6)
1898 BINARY_OP 3 (<<)
1900 BINARY_OP 7 (|)
1902 LOAD_CONST 51 (50381571)
1904 BINARY_OP 1 (&)
1906 BINARY_OP 7 (|)
1908 LOAD_DEREF 1 (reg)
1910 LOAD_ATTR 3 (NULL|self + get)
1912 LOAD_CONST 26 ("r1")
1914 CALL 1
1916 LOAD_DEREF 1 (reg)
1918 LOAD_ATTR 3 (NULL|self + get)
1920 LOAD_CONST 23 ("r0")
1922 CALL 1
1924 BINARY_SUBSCR
1926 LOAD_DEREF 1 (reg)
1928 LOAD_ATTR 3 (NULL|self + get)
1930 LOAD_CONST 33 ("r2")
1932 CALL 1
1934 LOAD_CONST 42 (3)
1936 BINARY_OP 5 (*)
1938 BINARY_SUBSCR
1940 LOAD_DEREF 1 (reg)
1942 LOAD_ATTR 3 (NULL|self + get)
1944 LOAD_CONST 26 ("r1")
1946 CALL 1
1948 LOAD_DEREF 1 (reg)
1950 LOAD_ATTR 3 (NULL|self + get)
1952 LOAD_CONST 23 ("r0")
1954 CALL 1
1956 BINARY_SUBSCR
1958 LOAD_DEREF 1 (reg)
1960 LOAD_ATTR 3 (NULL|self + get)
1962 LOAD_CONST 33 ("r2")
1964 CALL 1
1966 LOAD_CONST 42 (3)
1968 BINARY_OP 5 (*)
1970 BINARY_SUBSCR
1972 LOAD_CONST 42 (3)
1974 BINARY_OP 3 (<<)
1976 BINARY_OP 7 (|)
1978 LOAD_CONST 52 (153391689)
1980 BINARY_OP 1 (&)
1982 BINARY_OP 7 (|)

1984 LOAD_DEREF 1 (reg)
1986 LOAD_ATTR 3 (NULL|self + get)
1988 LOAD_CONST 26 ("r1")
1990 CALL 1
1992 LOAD_DEREF 1 (reg)
1994 LOAD_ATTR 3 (NULL|self + get)
1996 LOAD_CONST 23 ("r0")
1998 CALL 1
2000 BINARY_SUBSCR
2002 LOAD_DEREF 1 (reg)
2004 LOAD_ATTR 3 (NULL|self + get)
2006 LOAD_CONST 33 ("r2")
2008 CALL 1
2010 LOAD_CONST 42 (3)
2012 BINARY_OP 5 (*)
2014 LOAD_CONST 29 (1)
2016 BINARY_OP 0 (+)
2018 BINARY_SUBSCR
2020 LOAD_DEREF 1 (reg)
2022 LOAD_ATTR 3 (NULL|self + get)
2024 LOAD_CONST 26 ("r1")
2026 CALL 1
2028 LOAD_DEREF 1 (reg)
2030 LOAD_ATTR 3 (NULL|self + get)
2032 LOAD_CONST 23 ("r0")
2034 CALL 1
2036 BINARY_SUBSCR
2038 LOAD_DEREF 1 (reg)
2040 LOAD_ATTR 3 (NULL|self + get)
2042 LOAD_CONST 33 ("r2")
2044 CALL 1
2046 LOAD_CONST 42 (3)
2048 BINARY_OP 5 (*)
2050 LOAD_CONST 29 (1)
2052 BINARY_OP 0 (+)
2054 BINARY_SUBSCR
2056 LOAD_CONST 49 (12)
2058 BINARY_OP 3 (<<)
2060 BINARY_OP 7 (|)
2062 LOAD_CONST 50 (983055)
2064 BINARY_OP 1 (&)
2066 LOAD_DEREF 1 (reg)
2068 LOAD_ATTR 3 (NULL|self + get)
2070 LOAD_CONST 26 ("r1")
2072 CALL 1
2074 LOAD_DEREF 1 (reg)
2076 LOAD_ATTR 3 (NULL|self + get)
2078 LOAD_CONST 23 ("r0")
2080 CALL 1
2082 BINARY_SUBSCR
2084 LOAD_DEREF 1 (reg)
2086 LOAD_ATTR 3 (NULL|self + get)
2088 LOAD_CONST 33 ("r2")
2090 CALL 1
2092 LOAD_CONST 42 (3)
2094 BINARY_OP 5 (*)
2096 LOAD_CONST 29 (1)
2098 BINARY_OP 0 (+)
2100 BINARY_SUBSCR
2102 LOAD_DEREF 1 (reg)
2104 LOAD_ATTR 3 (NULL|self + get)
2106 LOAD_CONST 26 ("r1")
2108 CALL 1
2110 LOAD_DEREF 1 (reg)
2112 LOAD_ATTR 3 (NULL|self + get)
2114 LOAD_CONST 23 ("r0")
2116 CALL 1
2118 BINARY_SUBSCR
2120 LOAD_DEREF 1 (reg)
2122 LOAD_ATTR 3 (NULL|self + get)
2124 LOAD_CONST 33 ("r2")
2126 CALL 1
2128 LOAD_CONST 42 (3)
2130 BINARY_OP 5 (*)
2132 LOAD_CONST 29 (1)
2134 BINARY_OP 0 (+)
2136 BINARY_SUBSCR
2138 LOAD_CONST 27 (6)
2140 BINARY_OP 3 (<<)
2142 BINARY_OP 7 (|)
2144 LOAD_CONST 51 (50381571)
2146 BINARY_OP 1 (&)
2148 BINARY_OP 7 (|)
2150 LOAD_DEREF 1 (reg)
2152 LOAD_ATTR 3 (NULL|self + get)
2154 LOAD_CONST 26 ("r1")
2156 CALL 1
2158 LOAD_DEREF 1 (reg)
2160 LOAD_ATTR 3 (NULL|self + get)
2162 LOAD_CONST 23 ("r0")
2164 CALL 1
2166 BINARY_SUBSCR
2168 LOAD_DEREF 1 (reg)
2170 LOAD_ATTR 3 (NULL|self + get)
2172 LOAD_CONST 33 ("r2")
2174 CALL 1
2176 LOAD_CONST 42 (3)
2178 BINARY_OP 5 (*)
2180 LOAD_CONST 29 (1)
2182 BINARY_OP 0 (+)
2184 BINARY_SUBSCR
2186 LOAD_DEREF 1 (reg)
2188 LOAD_ATTR 3 (NULL|self + get)
2190 LOAD_CONST 26 ("r1")
2192 CALL 1
2194 LOAD_DEREF 1 (reg)
2196 LOAD_ATTR 3 (NULL|self + get)
2198 LOAD_CONST 23 ("r0")
2200 CALL 1
2202 BINARY_SUBSCR
2204 LOAD_DEREF 1 (reg)
2206 LOAD_ATTR 3 (NULL|self + get)
2208 LOAD_CONST 33 ("r2")
2210 CALL 1
2212 LOAD_CONST 42 (3)
2214 BINARY_OP 5 (*)
2216 LOAD_CONST 29 (1)
2218 BINARY_OP 0 (+)
2220 BINARY_SUBSCR
2222 LOAD_CONST 42 (3)
2224 BINARY_OP 3 (<<)
2226 BINARY_OP 7 (|)
2228 LOAD_CONST 52 (153391689)
2230 BINARY_OP 1 (&)
2232 BINARY_OP 7 (|)
2234 LOAD_CONST 29 (1)
2236 BINARY_OP 3 (<<)

2238 BINARY_OP 7 (|)

2240 LOAD_DEREF 1 (reg)
2242 LOAD_ATTR 3 (NULL|self + get)
2244 LOAD_CONST 26 ("r1")
2246 CALL 1
2248 LOAD_DEREF 1 (reg)
2250 LOAD_ATTR 3 (NULL|self + get)
2252 LOAD_CONST 23 ("r0")
2254 CALL 1
2256 BINARY_SUBSCR
2258 LOAD_DEREF 1 (reg)
2260 LOAD_ATTR 3 (NULL|self + get)
2262 LOAD_CONST 33 ("r2")
2264 CALL 1
2266 LOAD_CONST 42 (3)
2268 BINARY_OP 5 (*)
2270 LOAD_CONST 37 (2)
2272 BINARY_OP 0 (+)
2274 BINARY_SUBSCR
2276 LOAD_DEREF 1 (reg)
2278 LOAD_ATTR 3 (NULL|self + get)
2280 LOAD_CONST 26 ("r1")
2282 CALL 1
2284 LOAD_DEREF 1 (reg)
2286 LOAD_ATTR 3 (NULL|self + get)
2288 LOAD_CONST 23 ("r0")
2290 CALL 1
2292 BINARY_SUBSCR
2294 LOAD_DEREF 1 (reg)
2296 LOAD_ATTR 3 (NULL|self + get)
2298 LOAD_CONST 33 ("r2")
2300 CALL 1
2302 LOAD_CONST 42 (3)
2304 BINARY_OP 5 (*)
2306 LOAD_CONST 37 (2)
2308 BINARY_OP 0 (+)
2310 BINARY_SUBSCR
2312 LOAD_CONST 49 (12)
2314 BINARY_OP 3 (<<)
2316 BINARY_OP 7 (|)
2318 LOAD_CONST 50 (983055)
2320 BINARY_OP 1 (&)
2322 LOAD_DEREF 1 (reg)
2324 LOAD_ATTR 3 (NULL|self + get)
2326 LOAD_CONST 26 ("r1")
2328 CALL 1
2330 LOAD_DEREF 1 (reg)
2332 LOAD_ATTR 3 (NULL|self + get)
2334 LOAD_CONST 23 ("r0")
2336 CALL 1
2338 BINARY_SUBSCR
2340 LOAD_DEREF 1 (reg)
2342 LOAD_ATTR 3 (NULL|self + get)
2344 LOAD_CONST 33 ("r2")
2346 CALL 1
2348 LOAD_CONST 42 (3)
2350 BINARY_OP 5 (*)
2352 LOAD_CONST 37 (2)
2354 BINARY_OP 0 (+)
2356 BINARY_SUBSCR
2358 LOAD_DEREF 1 (reg)
2360 LOAD_ATTR 3 (NULL|self + get)
2362 LOAD_CONST 26 ("r1")
2364 CALL 1
2366 LOAD_DEREF 1 (reg)
2368 LOAD_ATTR 3 (NULL|self + get)
2370 LOAD_CONST 23 ("r0")
2372 CALL 1
2374 BINARY_SUBSCR
2376 LOAD_DEREF 1 (reg)
2378 LOAD_ATTR 3 (NULL|self + get)
2380 LOAD_CONST 33 ("r2")
2382 CALL 1
2384 LOAD_CONST 42 (3)
2386 BINARY_OP 5 (*)
2388 LOAD_CONST 37 (2)
2390 BINARY_OP 0 (+)
2392 BINARY_SUBSCR
2394 LOAD_CONST 27 (6)
2396 BINARY_OP 3 (<<)
2398 BINARY_OP 7 (|)
2400 LOAD_CONST 51 (50381571)
2402 BINARY_OP 1 (&)
2404 BINARY_OP 7 (|)
2406 LOAD_DEREF 1 (reg)
2408 LOAD_ATTR 3 (NULL|self + get)
2410 LOAD_CONST 26 ("r1")
2412 CALL 1
2414 LOAD_DEREF 1 (reg)
2416 LOAD_ATTR 3 (NULL|self + get)
2418 LOAD_CONST 23 ("r0")
2420 CALL 1
2422 BINARY_SUBSCR
2424 LOAD_DEREF 1 (reg)
2426 LOAD_ATTR 3 (NULL|self + get)
2428 LOAD_CONST 33 ("r2")
2430 CALL 1
2432 LOAD_CONST 42 (3)
2434 BINARY_OP 5 (*)
2436 LOAD_CONST 37 (2)
2438 BINARY_OP 0 (+)
2440 BINARY_SUBSCR
2442 LOAD_DEREF 1 (reg)
2444 LOAD_ATTR 3 (NULL|self + get)
2446 LOAD_CONST 26 ("r1")
2448 CALL 1
2450 LOAD_DEREF 1 (reg)
2452 LOAD_ATTR 3 (NULL|self + get)
2454 LOAD_CONST 23 ("r0")
2456 CALL 1
2458 BINARY_SUBSCR
2460 LOAD_DEREF 1 (reg)
2462 LOAD_ATTR 3 (NULL|self + get)
2464 LOAD_CONST 33 ("r2")
2466 CALL 1
2468 LOAD_CONST 42 (3)
2470 BINARY_OP 5 (*)
2472 LOAD_CONST 37 (2)
2474 BINARY_OP 0 (+)
2476 BINARY_SUBSCR
2478 LOAD_CONST 42 (3)
2480 BINARY_OP 3 (<<)
2482 BINARY_OP 7 (|)
2484 LOAD_CONST 52 (153391689)
2486 BINARY_OP 1 (&)
2488 BINARY_OP 7 (|)
2490 LOAD_CONST 37 (2)
2492 BINARY_OP 3 (<<)

2494 BINARY_OP 7 (|)

2496 CALL 2
2498 POP_TOP

2500 LOAD_DEREF 1 (reg)
2502 LOAD_ATTR 3 (NULL|self + get)
2504 LOAD_CONST 40 ("r5")
2506 CALL 1
2508 LOAD_DEREF 1 (reg)
2510 LOAD_ATTR 3 (NULL|self + get)
2512 LOAD_CONST 34 ("r4")
2514 CALL 1
2516 LOAD_DEREF 1 (reg)
2518 LOAD_ATTR 3 (NULL|self + get)
2520 LOAD_CONST 33 ("r2")
2522 CALL 1
2524 BINARY_SUBSCR
2526 COMPARE_OP 119 (!=)
2528 POP_JUMP_IF_FALSE 11 (to 2536)

2530 LOAD_GLOBAL 7 (NULL + destruction)
2532 LOAD_DEREF 1 (reg)
2534 CALL 1
2536 POP_TOP

2538 LOAD_DEREF 1 (reg)
2540 LOAD_ATTR 13 (NULL|self + set)
2542 LOAD_CONST 33 ("r2")
2544 LOAD_DEREF 1 (reg)
2546 LOAD_ATTR 3 (NULL|self + get)
2548 LOAD_CONST 33 ("r2")
2550 CALL 1
2552 LOAD_CONST 29 (1)
2554 BINARY_OP 0 (+)
2556 CALL 2
2558 POP_TOP

2560 LOAD_DEREF 1 (reg)
2562 LOAD_ATTR 3 (NULL|self + get)
2564 LOAD_CONST 33 ("r2")
2566 CALL 1
2568 LOAD_CONST 48 (9)
2570 COMPARE_OP 18 (<)
2572 POP_JUMP_IF_FALSE 3 (to 2576)
2574 JUMP_BACKWARD 1262 (to 1752)

2576 LOAD_DEREF 1 (reg)
2578 LOAD_ATTR 13 (NULL|self + set)
2580 LOAD_CONST 23 ("r0")
2582 LOAD_DEREF 1 (reg)
2584 LOAD_ATTR 3 (NULL|self + get)
2586 LOAD_CONST 23 ("r0")
2588 CALL 1
2590 LOAD_CONST 29 (1)
2592 BINARY_OP 0 (+)
2594 CALL 2
2596 POP_TOP
2598 JUMP_FORWARD 2754 (to 5010)

2600 LOAD_DEREF 1 (reg)
2602 LOAD_ATTR 3 (NULL|self + get)
2604 LOAD_CONST 23 ("r0")
2606 CALL 1
2608 LOAD_CONST 53 (5)
2610 COMPARE_OP 88 (==)
2612 POP_JUMP_IF_FALSE 2628 (to 4936)

2614 LOAD_DEREF 1 (reg)
2616 LOAD_ATTR 13 (NULL|self + set)
2618 LOAD_CONST 33 ("r2")
2620 LOAD_CONST 30 (0)
2622 CALL 2
2624 POP_TOP

2626 LOAD_DEREF 1 (reg)
2628 LOAD_ATTR 3 (NULL|self + get)
2630 LOAD_CONST 33 ("r2")
2632 CALL 1
2634 LOAD_CONST 28 (27)
2636 COMPARE_OP 18 (<)
2638 POP_JUMP_IF_FALSE 513 (to 2966)

2640 LOAD_DEREF 1 (reg)
2642 LOAD_ATTR 13 (NULL|self + set)

2644 LOAD_CONST 26 ("r1")
2646 LOAD_DEREF 1 (reg)
2648 LOAD_ATTR 3 (NULL|self + get)
2650 LOAD_CONST 26 ("r1")
2652 CALL 1
2654 LOAD_CONST 0 (None)
2656 LOAD_DEREF 1 (reg)
2658 LOAD_ATTR 3 (NULL|self + get)
2660 LOAD_CONST 23 ("r0")
2662 CALL 1
2664 BINARY_SLICE

2666 LOAD_DEREF 1 (reg)
2668 LOAD_ATTR 3 (NULL|self + get)
2670 LOAD_CONST 26 ("r1")
2672 CALL 1
2674 LOAD_DEREF 1 (reg)
2676 LOAD_ATTR 3 (NULL|self + get)
2678 LOAD_CONST 23 ("r0")
2680 CALL 1
2682 BINARY_SUBSCR
2684 LOAD_CONST 0 (None)
2686 LOAD_DEREF 1 (reg)
2688 LOAD_ATTR 3 (NULL|self + get)
2690 LOAD_CONST 33 ("r2")
2692 CALL 1
2694 BINARY_SLICE

2696 LOAD_GLOBAL 25 (NULL + bytes)
2698 LOAD_DEREF 1 (reg)
2700 LOAD_ATTR 3 (NULL|self + get)
2702 LOAD_CONST 26 ("r1")
2704 CALL 1
2706 LOAD_DEREF 1 (reg)
2708 LOAD_ATTR 3 (NULL|self + get)
2710 LOAD_CONST 23 ("r0")
2712 CALL 1
2714 BINARY_SUBSCR
2716 LOAD_DEREF 1 (reg)
2718 LOAD_ATTR 3 (NULL|self + get)
2720 LOAD_CONST 33 ("r2")
2722 CALL 1
2724 BINARY_SUBSCR
2726 LOAD_DEREF 1 (reg)
2728 LOAD_ATTR 3 (NULL|self + get)
2730 LOAD_CONST 26 ("r1")
2732 CALL 1
2734 LOAD_DEREF 1 (reg)
2736 LOAD_ATTR 3 (NULL|self + get)
2738 LOAD_CONST 23 ("r0")
2740 CALL 1
2742 BINARY_SUBSCR
2744 LOAD_DEREF 1 (reg)
2746 LOAD_ATTR 3 (NULL|self + get)
2748 LOAD_CONST 33 ("r2")
2750 CALL 1
2752 BINARY_SUBSCR
2754 LOAD_CONST 36 (13)
2756 BINARY_OP 10 (-)
2758 LOAD_DEREF 1 (reg)
2760 LOAD_ATTR 3 (NULL|self + get)
2762 LOAD_CONST 26 ("r1")
2764 CALL 1
2766 LOAD_DEREF 1 (reg)
2768 LOAD_ATTR 3 (NULL|self + get)
2770 LOAD_CONST 23 ("r0")
2772 CALL 1
2774 BINARY_SUBSCR
2776 LOAD_DEREF 1 (reg)
2778 LOAD_ATTR 3 (NULL|self + get)
2780 LOAD_CONST 33 ("r2")
2782 CALL 1
2784 BINARY_SUBSCR
2786 LOAD_CONST 49 (12)
2788 COMPARE_OP 148 (>)
2790 POP_JUMP_IF_FALSE 2 (to 2794)
2792 LOAD_CONST 29 (1)
2794 JUMP_FORWARD 1 (to 2798)
2796 LOAD_CONST 30 (0)
2798 BINARY_OP 0 (+)
2800 LOAD_CONST 37 (2)
2802 BINARY_OP 2 (//)
2804 LOAD_DEREF 1 (reg)
2806 LOAD_ATTR 3 (NULL|self + get)
2808 LOAD_CONST 26 ("r1")
2810 CALL 1
2812 LOAD_DEREF 1 (reg)
2814 LOAD_ATTR 3 (NULL|self + get)
2816 LOAD_CONST 23 ("r0")
2818 CALL 1
2820 BINARY_SUBSCR
2822 LOAD_DEREF 1 (reg)
2824 LOAD_ATTR 3 (NULL|self + get)
2826 LOAD_CONST 33 ("r2")
2828 CALL 1
2830 BINARY_SUBSCR
2832 LOAD_CONST 29 (1)
2834 BINARY_OP 1 (&)
2836 LOAD_CONST 30 (0)
2838 COMPARE_OP 88 (==)
2840 POP_JUMP_IF_FALSE 2 (to 2844)
2842 LOAD_CONST 38 (-1)
2844 JUMP_FORWARD 1 (to 2848)
2846 LOAD_CONST 29 (1)
2848 BINARY_OP 5 (*)
2850 BINARY_OP 0 (+)
2852 BUILD_LIST 1
2854 CALL 1

2856 BINARY_OP 0 (+)

2858 LOAD_DEREF 1 (reg)
2860 LOAD_ATTR 3 (NULL|self + get)
2862 LOAD_CONST 26 ("r1")
2864 CALL 1
2866 LOAD_DEREF 1 (reg)
2868 LOAD_ATTR 3 (NULL|self + get)
2870 LOAD_CONST 23 ("r0")
2872 CALL 1
2874 BINARY_SUBSCR
2876 LOAD_DEREF 1 (reg)
2878 LOAD_ATTR 3 (NULL|self + get)
2880 LOAD_CONST 33 ("r2")
2882 CALL 1
2884 LOAD_CONST 29 (1)
2886 BINARY_OP 0 (+)
2888 LOAD_CONST 0 (None)
2890 BINARY_SLICE

2892 BINARY_OP 0 (+)

2894 BUILD_LIST 1
2896 BINARY_OP 0 (+)

2898 LOAD_DEREF 1 (reg)
2900 LOAD_ATTR 3 (NULL|self + get)
2902 LOAD_CONST 26 ("r1")
2904 CALL 1
2906 LOAD_DEREF 1 (reg)
2908 LOAD_ATTR 3 (NULL|self + get)
2910 LOAD_CONST 23 ("r0")
2912 CALL 1
2914 LOAD_CONST 29 (1)
2916 BINARY_OP 0 (+)
2918 LOAD_CONST 0 (None)
2920 BINARY_SLICE

2922 BINARY_OP 0 (+)

2924 CALL 2
2926 POP_TOP

2928 LOAD_DEREF 1 (reg)
2930 LOAD_ATTR 13 (NULL|self + set)
2932 LOAD_CONST 33 ("r2")
2934 LOAD_DEREF 1 (reg)
2936 LOAD_ATTR 3 (NULL|self + get)
2938 LOAD_CONST 33 ("r2")
2940 CALL 1
2942 LOAD_CONST 29 (1)
2944 BINARY_OP 0 (+)
2946 CALL 2
2948 POP_TOP

2950 LOAD_DEREF 1 (reg)
2952 LOAD_ATTR 3 (NULL|self + get)
2954 LOAD_CONST 33 ("r2")
2956 CALL 1
2958 LOAD_CONST 28 (27)
2960 COMPARE_OP 18 (<)
2962 POP_JUMP_IF_FALSE 3 (to 2966)
2964 JUMP_BACKWARD 513 (to 2640)

2966 LOAD_DEREF 1 (reg)
2968 LOAD_ATTR 13 (NULL|self + set)
2970 LOAD_CONST 33 ("r2")
2972 BUILD_LIST 0
2974 CALL 2
2976 POP_TOP

2978 LOAD_DEREF 1 (reg)
2980 LOAD_ATTR 13 (NULL|self + set)
2982 LOAD_CONST 31 ("r3")
2984 BUILD_LIST 0
2986 LOAD_CONST 54 ((0, 26, 0))
2988 LIST_EXTEND 1
2990 BUILD_LIST 1
2992 CALL 2
2994 POP_TOP

2996 LOAD_GLOBAL 21 (NULL + len)
2998 LOAD_DEREF 1 (reg)
3000 LOAD_ATTR 3 (NULL|self + get)
3002 LOAD_CONST 31 ("r3")
3004 CALL 1
3006 CALL 1
3008 LOAD_CONST 30 (0)
3010 COMPARE_OP 148 (>)
3012 POP_JUMP_IF_FALSE 1387 (to 3876)

3014 LOAD_DEREF 1 (reg)
3016 LOAD_ATTR 13 (NULL|self + set)
3018 LOAD_CONST 34 ("r4")
3020 LOAD_DEREF 1 (reg)
3022 LOAD_ATTR 3 (NULL|self + get)
3024 LOAD_CONST 31 ("r3")
3026 CALL 1
3028 LOAD_CONST 38 (-1)
3030 BINARY_SUBSCR
3032 LOAD_CONST 30 (0)
3034 BINARY_SUBSCR
3036 CALL 2
3038 POP_TOP

3040 LOAD_DEREF 1 (reg)
3042 LOAD_ATTR 13 (NULL|self + set)
3044 LOAD_CONST 40 ("r5")
3046 LOAD_DEREF 1 (reg)
3048 LOAD_ATTR 3 (NULL|self + get)
3050 LOAD_CONST 31 ("r3")
3052 CALL 1
3054 LOAD_CONST 38 (-1)
3056 BINARY_SUBSCR
3058 LOAD_CONST 29 (1)
3060 BINARY_SUBSCR
3062 CALL 2
3064 POP_TOP

3066 LOAD_DEREF 1 (reg)
3068 LOAD_ATTR 13 (NULL|self + set)
3070 LOAD_CONST 55 ("r6")
3072 LOAD_DEREF 1 (reg)
3074 LOAD_ATTR 3 (NULL|self + get)
3076 LOAD_CONST 31 ("r3")
3078 CALL 1
3080 LOAD_CONST 38 (-1)
3082 BINARY_SUBSCR
3084 LOAD_CONST 37 (2)
3086 BINARY_SUBSCR
3088 CALL 2
3090 POP_TOP

3092 LOAD_DEREF 1 (reg)
3094 LOAD_ATTR 13 (NULL|self + set)
3096 LOAD_CONST 56 ("r7")
3098 LOAD_DEREF 1 (reg)
3100 LOAD_ATTR 3 (NULL|self + get)
3102 LOAD_CONST 34 ("r4")
3104 CALL 1
3106 LOAD_DEREF 1 (reg)
3108 LOAD_ATTR 3 (NULL|self + get)
3110 LOAD_CONST 40 ("r5")
3112 CALL 1
3114 BINARY_OP 0 (+)
3116 LOAD_CONST 37 (2)
3118 BINARY_OP 2 (//)
3120 CALL 2
3122 POP_TOP

3124 LOAD_DEREF 1 (reg)
3126 LOAD_ATTR 3 (NULL|self + get)
3128 LOAD_CONST 34 ("r4")
3130 CALL 1
3132 LOAD_DEREF 1 (reg)
3134 LOAD_ATTR 3 (NULL|self + get)
3136 LOAD_CONST 40 ("r5")
3138 CALL 1
3140 COMPARE_OP 188 (>=)
3142 POP_JUMP_IF_FALSE 39 (to 3170)

3144 LOAD_DEREF 1 (reg)
3146 LOAD_ATTR 13 (NULL|self + set)
3148 LOAD_CONST 31 ("r3")
3150 LOAD_DEREF 1 (reg)
3152 LOAD_ATTR 3 (NULL|self + get)
3154 LOAD_CONST 31 ("r3")
3156 CALL 1
3158 LOAD_CONST 0 (None)
3160 LOAD_CONST 38 (-1)
3162 BINARY_SLICE
3164 CALL 2
3166 POP_TOP

3168 JUMP_BACKWARD 277 (to 2994)

3170 LOAD_DEREF 1 (reg)
3172 LOAD_ATTR 3 (NULL|self + get)
3174 LOAD_CONST 55 ("r6")
3176 CALL 1
3178 LOAD_CONST 30 (0)
3180 COMPARE_OP 88 (==)
3182 POP_JUMP_IF_FALSE 145 (to 3274)

3184 LOAD_DEREF 1 (reg)
3186 LOAD_ATTR 13 (NULL|self + set)
3188 LOAD_CONST 31 ("r3")
3190 LOAD_DEREF 1 (reg)
3192 LOAD_ATTR 3 (NULL|self + get)
3194 LOAD_CONST 31 ("r3")
3196 CALL 1
3198 LOAD_CONST 0 (None)
3200 LOAD_CONST 38 (-1)
3202 BINARY_SLICE
3204 LOAD_DEREF 1 (reg)
3206 LOAD_ATTR 3 (NULL|self + get)
3208 LOAD_CONST 34 ("r4")
3210 CALL 1
3212 LOAD_DEREF 1 (reg)
3214 LOAD_ATTR 3 (NULL|self + get)
3216 LOAD_CONST 40 ("r5")
3218 CALL 1
3220 LOAD_CONST 29 (1)
3222 BUILD_LIST 3
3224 BUILD_LIST 1
3226 BINARY_OP 0 (+)
3228 CALL 2
3230 POP_TOP

3232 LOAD_DEREF 1 (reg)
3234 LOAD_ATTR 13 (NULL|self + set)
3236 LOAD_CONST 31 ("r3")
3238 LOAD_DEREF 1 (reg)
3240 LOAD_ATTR 3 (NULL|self + get)
3242 LOAD_CONST 31 ("r3")
3244 CALL 1
3246 LOAD_DEREF 1 (reg)
3248 LOAD_ATTR 3 (NULL|self + get)
3250 LOAD_CONST 34 ("r4")
3252 CALL 1
3254 LOAD_DEREF 1 (reg)
3256 LOAD_ATTR 3 (NULL|self + get)
3258 LOAD_CONST 56 ("r7")
3260 CALL 1
3262 LOAD_CONST 30 (0)
3264 BUILD_LIST 3
3266 BUILD_LIST 1
3268 BINARY_OP 0 (+)
3270 CALL 2
3272 POP_TOP
3274 JUMP_FORWARD 942 (to 3856)

3276 LOAD_DEREF 1 (reg)
3278 LOAD_ATTR 3 (NULL|self + get)
3280 LOAD_CONST 55 ("r6")
3282 CALL 1
3284 LOAD_CONST 29 (1)
3286 COMPARE_OP 88 (==)
3288 POP_JUMP_IF_FALSE 148 (to 3384)

3290 LOAD_DEREF 1 (reg)
3292 LOAD_ATTR 13 (NULL|self + set)
3294 LOAD_CONST 31 ("r3")
3296 LOAD_DEREF 1 (reg)
3298 LOAD_ATTR 3 (NULL|self + get)
3300 LOAD_CONST 31 ("r3")
3302 CALL 1
3304 LOAD_CONST 0 (None)
3306 LOAD_CONST 38 (-1)
3308 BINARY_SLICE
3310 LOAD_DEREF 1 (reg)
3312 LOAD_ATTR 3 (NULL|self + get)
3314 LOAD_CONST 34 ("r4")
3316 CALL 1
3318 LOAD_DEREF 1 (reg)
3320 LOAD_ATTR 3 (NULL|self + get)
3322 LOAD_CONST 40 ("r5")
3324 CALL 1
3326 LOAD_CONST 37 (2)
3328 BUILD_LIST 3
3330 BUILD_LIST 1
3332 BINARY_OP 0 (+)
3334 CALL 2
3336 POP_TOP

3338 LOAD_DEREF 1 (reg)
3340 LOAD_ATTR 13 (NULL|self + set)
3342 LOAD_CONST 31 ("r3")
3344 LOAD_DEREF 1 (reg)
3346 LOAD_ATTR 3 (NULL|self + get)
3348 LOAD_CONST 31 ("r3")
3350 CALL 1
3352 LOAD_DEREF 1 (reg)
3354 LOAD_ATTR 3 (NULL|self + get)
3356 LOAD_CONST 56 ("r7")
3358 CALL 1
3360 LOAD_CONST 29 (1)
3362 BINARY_OP 0 (+)
3364 LOAD_DEREF 1 (reg)
3366 LOAD_ATTR 3 (NULL|self + get)
3368 LOAD_CONST 40 ("r5")
3370 CALL 1
3372 LOAD_CONST 30 (0)
3374 BUILD_LIST 3
3376 BUILD_LIST 1
3378 BINARY_OP 0 (+)
3380 CALL 2
3382 POP_TOP
3384 JUMP_FORWARD 773 (to 3856)

3386 LOAD_DEREF 1 (reg)
3388 LOAD_ATTR 3 (NULL|self + get)
3390 LOAD_CONST 55 ("r6")
3392 CALL 1
3394 LOAD_CONST 37 (2)
3396 COMPARE_OP 88 (==)
3398 POP_JUMP_IF_FALSE 654 (to 3788)

3400 LOAD_DEREF 1 (reg)
3402 LOAD_ATTR 3 (NULL|self + get)
3404 LOAD_CONST 26 ("r1")
3406 CALL 1
3408 LOAD_DEREF 1 (reg)
3410 LOAD_ATTR 3 (NULL|self + get)
3412 LOAD_CONST 23 ("r0")
3414 CALL 1
3416 BINARY_SUBSCR
3418 LOAD_DEREF 1 (reg)
3420 LOAD_ATTR 3 (NULL|self + get)
3422 LOAD_CONST 40 ("r5")
3424 CALL 1
3426 BINARY_SUBSCR
3428 LOAD_DEREF 1 (reg)
3430 LOAD_ATTR 3 (NULL|self + get)
3432 LOAD_CONST 26 ("r1")
3434 CALL 1
3436 LOAD_DEREF 1 (reg)
3438 LOAD_ATTR 3 (NULL|self + get)
3440 LOAD_CONST 23 ("r0")
3442 CALL 1
3444 BINARY_SUBSCR
3446 LOAD_DEREF 1 (reg)
3448 LOAD_ATTR 3 (NULL|self + get)
3450 LOAD_CONST 56 ("r7")
3452 CALL 1
3454 BINARY_SUBSCR
3456 COMPARE_OP 18 (<)
3458 POP_JUMP_IF_FALSE 471 (to 3738)

3460 LOAD_DEREF 1 (reg)
3462 LOAD_ATTR 13 (NULL|self + set)

3464 LOAD_CONST 26 ("r1")
3466 LOAD_DEREF 1 (reg)
3468 LOAD_ATTR 3 (NULL|self + get)
3470 LOAD_CONST 26 ("r1")
3472 CALL 1
3474 LOAD_CONST 0 (None)
3476 LOAD_DEREF 1 (reg)
3478 LOAD_ATTR 3 (NULL|self + get)
3480 LOAD_CONST 23 ("r0")
3482 CALL 1
3484 BINARY_SLICE

3486 LOAD_DEREF 1 (reg)
3488 LOAD_ATTR 3 (NULL|self + get)
3490 LOAD_CONST 26 ("r1")
3492 CALL 1
3494 LOAD_DEREF 1 (reg)
3496 LOAD_ATTR 3 (NULL|self + get)
3498 LOAD_CONST 23 ("r0")
3500 CALL 1
3502 BINARY_SUBSCR
3504 LOAD_CONST 0 (None)
3506 LOAD_DEREF 1 (reg)
3508 LOAD_ATTR 3 (NULL|self + get)
3510 LOAD_CONST 56 ("r7")
3512 CALL 1
3514 BINARY_SLICE

3516 LOAD_GLOBAL 25 (NULL + bytes)
3518 LOAD_DEREF 1 (reg)
3520 LOAD_ATTR 3 (NULL|self + get)
3522 LOAD_CONST 26 ("r1")
3524 CALL 1
3526 LOAD_DEREF 1 (reg)
3528 LOAD_ATTR 3 (NULL|self + get)
3530 LOAD_CONST 23 ("r0")
3532 CALL 1
3534 BINARY_SUBSCR
3536 LOAD_DEREF 1 (reg)
3538 LOAD_ATTR 3 (NULL|self + get)
3540 LOAD_CONST 40 ("r5")
3542 CALL 1
3544 BINARY_SUBSCR
3546 BUILD_LIST 1
3548 CALL 1

3550 BINARY_OP 0 (+)

3552 LOAD_DEREF 1 (reg)
3554 LOAD_ATTR 3 (NULL|self + get)
3556 LOAD_CONST 26 ("r1")
3558 CALL 1
3560 LOAD_DEREF 1 (reg)
3562 LOAD_ATTR 3 (NULL|self + get)
3564 LOAD_CONST 23 ("r0")
3566 CALL 1
3568 BINARY_SUBSCR
3570 LOAD_DEREF 1 (reg)
3572 LOAD_ATTR 3 (NULL|self + get)
3574 LOAD_CONST 56 ("r7")
3576 CALL 1
3578 LOAD_CONST 29 (1)
3580 BINARY_OP 0 (+)
3582 LOAD_DEREF 1 (reg)
3584 LOAD_ATTR 3 (NULL|self + get)
3586 LOAD_CONST 40 ("r5")
3588 CALL 1
3590 BINARY_SLICE

3592 BINARY_OP 0 (+)

3594 LOAD_GLOBAL 25 (NULL + bytes)
3596 LOAD_DEREF 1 (reg)
3598 LOAD_ATTR 3 (NULL|self + get)
3600 LOAD_CONST 26 ("r1")
3602 CALL 1
3604 LOAD_DEREF 1 (reg)
3606 LOAD_ATTR 3 (NULL|self + get)
3608 LOAD_CONST 23 ("r0")
3610 CALL 1
3612 BINARY_SUBSCR
3614 LOAD_DEREF 1 (reg)
3616 LOAD_ATTR 3 (NULL|self + get)
3618 LOAD_CONST 56 ("r7")
3620 CALL 1
3622 BINARY_SUBSCR
3624 BUILD_LIST 1
3626 CALL 1

3628 BINARY_OP 0 (+)

3630 LOAD_DEREF 1 (reg)
3632 LOAD_ATTR 3 (NULL|self + get)
3634 LOAD_CONST 26 ("r1")
3636 CALL 1
3638 LOAD_DEREF 1 (reg)
3640 LOAD_ATTR 3 (NULL|self + get)
3642 LOAD_CONST 23 ("r0")
3644 CALL 1
3646 BINARY_SUBSCR
3648 LOAD_DEREF 1 (reg)
3650 LOAD_ATTR 3 (NULL|self + get)
3652 LOAD_CONST 40 ("r5")
3654 CALL 1
3656 LOAD_CONST 29 (1)
3658 BINARY_OP 0 (+)
3660 LOAD_CONST 0 (None)
3662 BINARY_SLICE

3664 BINARY_OP 0 (+)

3666 BUILD_LIST 1
3668 BINARY_OP 0 (+)

3670 LOAD_DEREF 1 (reg)
3672 LOAD_ATTR 3 (NULL|self + get)
3674 LOAD_CONST 26 ("r1")
3676 CALL 1
3678 LOAD_DEREF 1 (reg)
3680 LOAD_ATTR 3 (NULL|self + get)
3682 LOAD_CONST 23 ("r0")
3684 CALL 1
3686 LOAD_CONST 29 (1)
3688 BINARY_OP 0 (+)
3690 LOAD_CONST 0 (None)
3692 BINARY_SLICE

3694 BINARY_OP 0 (+)

3696 CALL 2
3698 POP_TOP

3700 LOAD_DEREF 1 (reg)
3702 LOAD_ATTR 13 (NULL|self + set)
3704 LOAD_CONST 33 ("r2")
3706 LOAD_DEREF 1 (reg)
3708 LOAD_ATTR 3 (NULL|self + get)
3710 LOAD_CONST 33 ("r2")
3712 CALL 1
3714 LOAD_DEREF 1 (reg)
3716 LOAD_ATTR 3 (NULL|self + get)
3718 LOAD_CONST 56 ("r7")
3720 CALL 1
3722 LOAD_DEREF 1 (reg)
3724 LOAD_ATTR 3 (NULL|self + get)
3726 LOAD_CONST 40 ("r5")
3728 CALL 1
3730 BUILD_LIST 2
3732 BUILD_LIST 1
3734 BINARY_OP 0 (+)
3736 CALL 2
3738 POP_TOP

3740 LOAD_DEREF 1 (reg)
3742 LOAD_ATTR 13 (NULL|self + set)
3744 LOAD_CONST 31 ("r3")
3746 LOAD_DEREF 1 (reg)
3748 LOAD_ATTR 3 (NULL|self + get)
3750 LOAD_CONST 31 ("r3")
3752 CALL 1
3754 LOAD_CONST 0 (None)
3756 LOAD_CONST 38 (-1)
3758 BINARY_SLICE
3760 LOAD_DEREF 1 (reg)
3762 LOAD_ATTR 3 (NULL|self + get)
3764 LOAD_CONST 34 ("r4")
3766 CALL 1
3768 LOAD_DEREF 1 (reg)
3770 LOAD_ATTR 3 (NULL|self + get)
3772 LOAD_CONST 40 ("r5")
3774 CALL 1
3776 LOAD_CONST 42 (3)
3778 BUILD_LIST 3
3780 BUILD_LIST 1
3782 BINARY_OP 0 (+)
3784 CALL 2
3786 POP_TOP
3788 JUMP_FORWARD 97 (to 3856)

3790 LOAD_DEREF 1 (reg)
3792 LOAD_ATTR 3 (NULL|self + get)
3794 LOAD_CONST 55 ("r6")
3796 CALL 1
3798 LOAD_CONST 42 (3)
3800 COMPARE_OP 88 (==)
3802 POP_JUMP_IF_FALSE 76 (to 3854)

3804 LOAD_DEREF 1 (reg)
3806 LOAD_ATTR 13 (NULL|self + set)
3808 LOAD_CONST 31 ("r3")
3810 LOAD_DEREF 1 (reg)
3812 LOAD_ATTR 3 (NULL|self + get)
3814 LOAD_CONST 31 ("r3")
3816 CALL 1
3818 LOAD_CONST 0 (None)
3820 LOAD_CONST 38 (-1)
3822 BINARY_SLICE
3824 LOAD_DEREF 1 (reg)
3826 LOAD_ATTR 3 (NULL|self + get)
3828 LOAD_CONST 34 ("r4")
3830 CALL 1
3832 LOAD_DEREF 1 (reg)
3834 LOAD_ATTR 3 (NULL|self + get)
3836 LOAD_CONST 40 ("r5")
3838 CALL 1
3840 LOAD_CONST 29 (1)
3842 BINARY_OP 10 (-)
3844 LOAD_CONST 30 (0)
3846 BUILD_LIST 3
3848 BUILD_LIST 1
3850 BINARY_OP 0 (+)
3852 CALL 2
3854 POP_TOP

3856 LOAD_GLOBAL 21 (NULL + len)
3858 LOAD_DEREF 1 (reg)
3860 LOAD_ATTR 3 (NULL|self + get)
3862 LOAD_CONST 31 ("r3")
3864 CALL 1
3866 CALL 1
3868 LOAD_CONST 30 (0)
3870 COMPARE_OP 148 (>)
3872 POP_JUMP_IF_FALSE 3 (to 3876)
3874 JUMP_BACKWARD 1387 (to 3014)

3876 LOAD_DEREF 1 (reg)
3878 LOAD_ATTR 3 (NULL|self + get)
3880 LOAD_CONST 26 ("r1")
3882 CALL 1
3884 LOAD_DEREF 1 (reg)
3886 LOAD_ATTR 3 (NULL|self + get)
3888 LOAD_CONST 23 ("r0")
3890 CALL 1
3892 BINARY_SUBSCR
3894 LOAD_GLOBAL 25 (NULL + bytes)
3896 BUILD_LIST 0
3898 LOAD_CONST 57 ((30, 30, 32, 40, 42, 45, 45, 45, 46, 67, 70, 70, 70, 70, 73, 76, 76, 76, 76, 94, 109, 136, 136, 136, 136, 136, 181))
3900 LIST_EXTEND 1
3902 CALL 1
3904 COMPARE_OP 119 (!=)
3906 POP_JUMP_IF_FALSE 11 (to 3914)

3908 LOAD_GLOBAL 7 (NULL + destruction)
3910 LOAD_DEREF 1 (reg)
3912 CALL 1
3914 POP_TOP

3916 LOAD_DEREF 1 (reg)
3918 LOAD_ATTR 3 (NULL|self + get)
3920 LOAD_CONST 33 ("r2")
3922 CALL 1
3924 BUILD_LIST 0
3926 LOAD_CONST 37 (2)
3928 LOAD_CONST 42 (3)
3930 BUILD_LIST 2
3932 LIST_APPEND 1
3934 LOAD_CONST 29 (1)
3936 LOAD_CONST 42 (3)
3938 BUILD_LIST 2
3940 LIST_APPEND 1
3942 LOAD_CONST 29 (1)
3944 LOAD_CONST 37 (2)
3946 BUILD_LIST 2
3948 LIST_APPEND 1
3950 LOAD_CONST 30 (0)
3952 LOAD_CONST 29 (1)
3954 BUILD_LIST 2
3956 LIST_APPEND 1
3958 LOAD_CONST 46 (4)
3960 LOAD_CONST 53 (5)
3962 BUILD_LIST 2
3964 LIST_APPEND 1
3966 LOAD_CONST 53 (5)
3968 LOAD_CONST 27 (6)
3970 BUILD_LIST 2
3972 LIST_APPEND 1
3974 LOAD_CONST 46 (4)
3976 LOAD_CONST 53 (5)
3978 BUILD_LIST 2
3980 LIST_APPEND 1
3982 LOAD_CONST 42 (3)
3984 LOAD_CONST 27 (6)
3986 BUILD_LIST 2
3988 LIST_APPEND 1
3990 LOAD_CONST 42 (3)
3992 LOAD_CONST 46 (4)
3994 BUILD_LIST 2
3996 LIST_APPEND 1
3998 LOAD_CONST 46 (4)
4000 LOAD_CONST 53 (5)
4002 BUILD_LIST 2
4004 LIST_APPEND 1
4006 LOAD_CONST 37 (2)
4008 LOAD_CONST 46 (4)
4010 BUILD_LIST 2
4012 LIST_APPEND 1
4014 LOAD_CONST 37 (2)
4016 LOAD_CONST 42 (3)
4018 BUILD_LIST 2
4020 LIST_APPEND 1
4022 LOAD_CONST 29 (1)
4024 LOAD_CONST 42 (3)
4026 BUILD_LIST 2
4028 LIST_APPEND 1
4030 LOAD_CONST 29 (1)
4032 LOAD_CONST 37 (2)
4034 BUILD_LIST 2
4036 LIST_APPEND 1
4038 LOAD_CONST 8 (8)
4040 LOAD_CONST 48 (9)
4042 BUILD_LIST 2
4044 LIST_APPEND 1
4046 LOAD_CONST 58 (11)
4048 LOAD_CONST 49 (12)
4050 BUILD_LIST 2
4052 LIST_APPEND 1
4054 LOAD_CONST 49 (12)
4056 LOAD_CONST 36 (13)
4058 BUILD_LIST 2
4060 LIST_APPEND 1
4062 LOAD_CONST 58 (11)
4064 LOAD_CONST 49 (12)
4066 BUILD_LIST 2
4068 LIST_APPEND 1
4070 LOAD_CONST 59 (10)
4072 LOAD_CONST 58 (11)
4074 BUILD_LIST 2
4076 LIST_APPEND 1
4078 LOAD_CONST 48 (9)
4080 LOAD_CONST 59 (10)
4082 BUILD_LIST 2
4084 LIST_APPEND 1
4086 LOAD_CONST 8 (8)
4088 LOAD_CONST 48 (9)
4090 BUILD_LIST 2
4092 LIST_APPEND 1
4094 LOAD_CONST 60 (7)
4096 LOAD_CONST 8 (8)
4098 BUILD_LIST 2
4100 LIST_APPEND 1
4102 LOAD_CONST 27 (6)
4104 LOAD_CONST 49 (12)
4106 BUILD_LIST 2
4108 LIST_APPEND 1
4110 LOAD_CONST 27 (6)
4112 LOAD_CONST 60 (7)
4114 BUILD_LIST 2
4116 LIST_APPEND 1
4118 LOAD_CONST 60 (7)
4120 LOAD_CONST 8 (8)
4122 BUILD_LIST 2
4124 LIST_APPEND 1
4126 LOAD_CONST 8 (8)
4128 LOAD_CONST 59 (10)
4130 BUILD_LIST 2
4132 LIST_APPEND 1
4134 LOAD_CONST 8 (8)
4136 LOAD_CONST 48 (9)
4138 BUILD_LIST 2
4140 LIST_APPEND 1
4142 LOAD_CONST 53 (5)
4144 LOAD_CONST 58 (11)
4146 BUILD_LIST 2
4148 LIST_APPEND 1
4150 LOAD_CONST 46 (4)
4152 LOAD_CONST 53 (5)
4154 BUILD_LIST 2
4156 LIST_APPEND 1
4158 LOAD_CONST 53 (5)
4160 LOAD_CONST 59 (10)
4162 BUILD_LIST 2
4164 LIST_APPEND 1
4166 LOAD_CONST 53 (5)
4168 LOAD_CONST 27 (6)
4170 BUILD_LIST 2
4172 LIST_APPEND 1
4174 LOAD_CONST 27 (6)
4176 LOAD_CONST 60 (7)
4178 BUILD_LIST 2
4180 LIST_APPEND 1
4182 LOAD_CONST 60 (7)
4184 LOAD_CONST 48 (9)
4186 BUILD_LIST 2
4188 LIST_APPEND 1
4190 LOAD_CONST 60 (7)
4192 LOAD_CONST 8 (8)
4194 BUILD_LIST 2
4196 LIST_APPEND 1
4198 LOAD_CONST 46 (4)
4200 LOAD_CONST 8 (8)
4202 BUILD_LIST 2
4204 LIST_APPEND 1
4206 LOAD_CONST 46 (4)
4208 LOAD_CONST 53 (5)
4210 BUILD_LIST 2
4212 LIST_APPEND 1
4214 LOAD_CONST 53 (5)
4216 LOAD_CONST 60 (7)
4218 BUILD_LIST 2
4220 LIST_APPEND 1
4222 LOAD_CONST 42 (3)
4224 LOAD_CONST 27 (6)
4226 BUILD_LIST 2
4228 LIST_APPEND 1
4230 LOAD_CONST 42 (3)
4232 LOAD_CONST 46 (4)
4234 BUILD_LIST 2
4236 LIST_APPEND 1
4238 LOAD_CONST 37 (2)
4240 LOAD_CONST 53 (5)
4242 BUILD_LIST 2
4244 LIST_APPEND 1
4246 LOAD_CONST 37 (2)
4248 LOAD_CONST 42 (3)
4250 BUILD_LIST 2
4252 LIST_APPEND 1
4254 LOAD_CONST 44 (16)
4256 LOAD_CONST 61 (17)
4258 BUILD_LIST 2
4260 LIST_APPEND 1
4262 LOAD_CONST 62 (15)
4264 LOAD_CONST 44 (16)
4266 BUILD_LIST 2
4268 LIST_APPEND 1
4270 LOAD_CONST 63 (19)
4272 LOAD_CONST 64 (20)
4274 BUILD_LIST 2
4276 LIST_APPEND 1
4278 LOAD_CONST 65 (18)
4280 LOAD_CONST 63 (19)
4282 BUILD_LIST 2
4284 LIST_APPEND 1
4286 LOAD_CONST 61 (17)
4288 LOAD_CONST 64 (20)
4290 BUILD_LIST 2
4292 LIST_APPEND 1
4294 LOAD_CONST 61 (17)
4296 LOAD_CONST 65 (18)
4298 BUILD_LIST 2
4300 LIST_APPEND 1
4302 LOAD_CONST 44 (16)
4304 LOAD_CONST 63 (19)
4306 BUILD_LIST 2
4308 LIST_APPEND 1
4310 LOAD_CONST 44 (16)
4312 LOAD_CONST 61 (17)
4314 BUILD_LIST 2
4316 LIST_APPEND 1
4318 LOAD_CONST 62 (15)
4320 LOAD_CONST 44 (16)
4322 BUILD_LIST 2
4324 LIST_APPEND 1
4326 LOAD_CONST 66 (22)
4328 LOAD_CONST 67 (23)
4330 BUILD_LIST 2
4332 LIST_APPEND 1
4334 LOAD_CONST 68 (21)
4336 LOAD_CONST 66 (22)
4338 BUILD_LIST 2
4340 LIST_APPEND 1
4342 LOAD_CONST 67 (23)
4344 LOAD_CONST 69 (24)
4346 BUILD_LIST 2
4348 LIST_APPEND 1
4350 LOAD_CONST 64 (20)
4352 LOAD_CONST 68 (21)
4354 BUILD_LIST 2
4356 LIST_APPEND 1
4358 LOAD_CONST 68 (21)
4360 LOAD_CONST 66 (22)
4362 BUILD_LIST 2
4364 LIST_APPEND 1
4366 LOAD_CONST 66 (22)
4368 LOAD_CONST 67 (23)
4370 BUILD_LIST 2
4372 LIST_APPEND 1
4374 LOAD_CONST 63 (19)
4376 LOAD_CONST 64 (20)
4378 BUILD_LIST 2
4380 LIST_APPEND 1
4382 LOAD_CONST 64 (20)
4384 LOAD_CONST 68 (21)
4386 BUILD_LIST 2
4388 LIST_APPEND 1
4390 LOAD_CONST 65 (18)
4392 LOAD_CONST 63 (19)
4394 BUILD_LIST 2
4396 LIST_APPEND 1
4398 LOAD_CONST 61 (17)
4400 LOAD_CONST 65 (18)
4402 BUILD_LIST 2
4404 LIST_APPEND 1
4406 LOAD_CONST 36 (13)
4408 LOAD_CONST 70 (14)
4410 BUILD_LIST 2
4412 LIST_APPEND 1
4414 LOAD_CONST 70 (14)
4416 LOAD_CONST 44 (16)
4418 BUILD_LIST 2
4420 LIST_APPEND 1
4422 LOAD_CONST 70 (14)
4424 LOAD_CONST 62 (15)
4426 BUILD_LIST 2
4428 LIST_APPEND 1
4430 LOAD_CONST 44 (16)
4432 LOAD_CONST 63 (19)
4434 BUILD_LIST 2
4436 LIST_APPEND 1
4438 LOAD_CONST 44 (16)
4440 LOAD_CONST 61 (17)
4442 BUILD_LIST 2
4444 LIST_APPEND 1
4446 LOAD_CONST 63 (19)
4448 LOAD_CONST 64 (20)
4450 BUILD_LIST 2
4452 LIST_APPEND 1
4454 LOAD_CONST 64 (20)
4456 LOAD_CONST 68 (21)
4458 BUILD_LIST 2
4460 LIST_APPEND 1
4462 LOAD_CONST 68 (21)
4464 LOAD_CONST 66 (22)
4466 BUILD_LIST 2
4468 LIST_APPEND 1
4470 LOAD_CONST 49 (12)
4472 LOAD_CONST 36 (13)
4474 BUILD_LIST 2
4476 LIST_APPEND 1
4478 LOAD_CONST 36 (13)
4480 LOAD_CONST 70 (14)
4482 BUILD_LIST 2
4484 LIST_APPEND 1
4486 LOAD_CONST 70 (14)
4488 LOAD_CONST 61 (17)
4490 BUILD_LIST 2
4492 LIST_APPEND 1
4494 LOAD_CONST 70 (14)
4496 LOAD_CONST 44 (16)
4498 BUILD_LIST 2
4500 LIST_APPEND 1
4502 LOAD_CONST 70 (14)
4504 LOAD_CONST 62 (15)
4506 BUILD_LIST 2
4508 LIST_APPEND 1
4510 LOAD_CONST 61 (17)
4512 LOAD_CONST 65 (18)
4514 BUILD_LIST 2
4516 LIST_APPEND 1
4518 LOAD_CONST 65 (18)
4520 LOAD_CONST 63 (19)
4522 BUILD_LIST 2
4524 LIST_APPEND 1
4526 LOAD_CONST 63 (19)
4528 LOAD_CONST 68 (21)
4530 BUILD_LIST 2
4532 LIST_APPEND 1
4534 LOAD_CONST 58 (11)
4536 LOAD_CONST 49 (12)
4538 BUILD_LIST 2
4540 LIST_APPEND 1
4542 LOAD_CONST 49 (12)
4544 LOAD_CONST 36 (13)
4546 BUILD_LIST 2
4548 LIST_APPEND 1
4550 LOAD_CONST 36 (13)
4552 LOAD_CONST 44 (16)
4554 BUILD_LIST 2
4556 LIST_APPEND 1
4558 LOAD_CONST 36 (13)
4560 LOAD_CONST 62 (15)
4562 BUILD_LIST 2
4564 LIST_APPEND 1
4566 LOAD_CONST 36 (13)
4568 LOAD_CONST 70 (14)
4570 BUILD_LIST 2
4572 LIST_APPEND 1
4574 LOAD_CONST 44 (16)
4576 LOAD_CONST 61 (17)
4578 BUILD_LIST 2
4580 LIST_APPEND 1
4582 LOAD_CONST 61 (17)
4584 LOAD_CONST 65 (18)
4586 BUILD_LIST 2
4588 LIST_APPEND 1
4590 LOAD_CONST 65 (18)
4592 LOAD_CONST 64 (20)
4594 BUILD_LIST 2
4596 LIST_APPEND 1
4598 LOAD_CONST 59 (10)
4600 LOAD_CONST 58 (11)
4602 BUILD_LIST 2
4604 LIST_APPEND 1
4606 LOAD_CONST 58 (11)
4608 LOAD_CONST 49 (12)
4610 BUILD_LIST 2
4612 LIST_APPEND 1
4614 LOAD_CONST 49 (12)
4616 LOAD_CONST 70 (14)
4618 BUILD_LIST 2
4620 LIST_APPEND 1
4622 LOAD_CONST 49 (12)
4624 LOAD_CONST 36 (13)
4626 BUILD_LIST 2
4628 LIST_APPEND 1
4630 LOAD_CONST 70 (14)
4632 LOAD_CONST 63 (19)
4634 BUILD_LIST 2
4636 LIST_APPEND 1
4638 LOAD_CONST 70 (14)
4640 LOAD_CONST 62 (15)
4642 BUILD_LIST 2
4644 LIST_APPEND 1
4646 LOAD_CONST 62 (15)
4648 LOAD_CONST 61 (17)
4650 BUILD_LIST 2
4652 LIST_APPEND 1
4654 LOAD_CONST 62 (15)
4656 LOAD_CONST 44 (16)
4658 BUILD_LIST 2
4660 LIST_APPEND 1
4662 LOAD_CONST 48 (9)
4664 LOAD_CONST 59 (10)
4666 BUILD_LIST 2
4668 LIST_APPEND 1
4670 LOAD_CONST 59 (10)
4672 LOAD_CONST 58 (11)
4674 BUILD_LIST 2
4676 LIST_APPEND 1
4678 LOAD_CONST 58 (11)
4680 LOAD_CONST 36 (13)
4682 BUILD_LIST 2
4684 LIST_APPEND 1
4686 LOAD_CONST 58 (11)
4688 LOAD_CONST 49 (12)
4690 BUILD_LIST 2
4692 LIST_APPEND 1
4694 LOAD_CONST 36 (13)
4696 LOAD_CONST 70 (14)
4698 BUILD_LIST 2
4700 LIST_APPEND 1
4702 LOAD_CONST 70 (14)
4704 LOAD_CONST 44 (16)
4706 BUILD_LIST 2
4708 LIST_APPEND 1
4710 LOAD_CONST 70 (14)
4712 LOAD_CONST 62 (15)
4714 BUILD_LIST 2
4716 LIST_APPEND 1
4718 LOAD_CONST 8 (8)
4720 LOAD_CONST 48 (9)
4722 BUILD_LIST 2
4724 LIST_APPEND 1
4726 LOAD_CONST 48 (9)
4728 LOAD_CONST 58 (11)
4730 BUILD_LIST 2
4732 LIST_APPEND 1
4734 LOAD_CONST 48 (9)
4736 LOAD_CONST 59 (10)
4738 BUILD_LIST 2
4740 LIST_APPEND 1
4742 LOAD_CONST 58 (11)
4744 LOAD_CONST 62 (15)
4746 BUILD_LIST 2
4748 LIST_APPEND 1
4750 LOAD_CONST 58 (11)
4752 LOAD_CONST 70 (14)
4754 BUILD_LIST 2
4756 LIST_APPEND 1
4758 LOAD_CONST 58 (11)
4760 LOAD_CONST 49 (12)
4762 BUILD_LIST 2
4764 LIST_APPEND 1
4766 LOAD_CONST 60 (7)
4768 LOAD_CONST 8 (8)
4770 BUILD_LIST 2
4772 LIST_APPEND 1
4774 LOAD_CONST 8 (8)
4776 LOAD_CONST 59 (10)
4778 BUILD_LIST 2
4780 LIST_APPEND 1
4782 LOAD_CONST 8 (8)
4784 LOAD_CONST 48 (9)
4786 BUILD_LIST 2
4788 LIST_APPEND 1
4790 LOAD_CONST 59 (10)
4792 LOAD_CONST 58 (11)
4794 BUILD_LIST 2
4796 LIST_APPEND 1
4798 LOAD_CONST 27 (6)
4800 LOAD_CONST 60 (7)
4802 BUILD_LIST 2
4804 LIST_APPEND 1
4806 LOAD_CONST 60 (7)
4808 LOAD_CONST 8 (8)
4810 BUILD_LIST 2
4812 LIST_APPEND 1
4814 LOAD_CONST 8 (8)
4816 LOAD_CONST 59 (10)
4818 BUILD_LIST 2
4820 LIST_APPEND 1
4822 LOAD_CONST 8 (8)
4824 LOAD_CONST 48 (9)
4826 BUILD_LIST 2
4828 LIST_APPEND 1
4830 LOAD_CONST 53 (5)
4832 LOAD_CONST 27 (6)
4834 BUILD_LIST 2
4836 LIST_APPEND 1
4838 LOAD_CONST 27 (6)
4840 LOAD_CONST 60 (7)
4842 BUILD_LIST 2
4844 LIST_APPEND 1
4846 LOAD_CONST 60 (7)
4848 LOAD_CONST 8 (8)
4850 BUILD_LIST 2
4852 LIST_APPEND 1
4854 LOAD_CONST 46 (4)
4856 LOAD_CONST 53 (5)
4858 BUILD_LIST 2
4860 LIST_APPEND 1
4862 LOAD_CONST 53 (5)
4864 LOAD_CONST 27 (6)
4866 BUILD_LIST 2
4868 LIST_APPEND 1
4870 LOAD_CONST 42 (3)
4872 LOAD_CONST 46 (4)
4874 BUILD_LIST 2
4876 LIST_APPEND 1
4878 LOAD_CONST 46 (4)
4880 LOAD_CONST 53 (5)
4882 BUILD_LIST 2
4884 LIST_APPEND 1
4886 LOAD_CONST 37 (2)
4888 LOAD_CONST 46 (4)
4890 BUILD_LIST 2
4892 LIST_APPEND 1
4894 LOAD_CONST 37 (2)
4896 LOAD_CONST 42 (3)
4898 BUILD_LIST 2
4900 LIST_APPEND 1
4902 COMPARE_OP 119 (!=)
4904 POP_JUMP_IF_FALSE 11 (to 4912)

4906 LOAD_GLOBAL 7 (NULL + destruction)
4908 LOAD_DEREF 1 (reg)
4910 CALL 1
4912 POP_TOP

4914 LOAD_DEREF 1 (reg)
4916 LOAD_ATTR 13 (NULL|self + set)
4918 LOAD_CONST 23 ("r0")
4920 LOAD_DEREF 1 (reg)
4922 LOAD_ATTR 3 (NULL|self + get)
4924 LOAD_CONST 23 ("r0")
4926 CALL 1
4928 LOAD_CONST 29 (1)
4930 BINARY_OP 0 (+)
4932 CALL 2
4934 POP_TOP
4936 JUMP_FORWARD 104 (to 5010)

4938 LOAD_DEREF 1 (reg)
4940 LOAD_ATTR 3 (NULL|self + get)
4942 LOAD_CONST 23 ("r0")
4944 CALL 1
4946 LOAD_CONST 27 (6)
4948 COMPARE_OP 88 (==)
4950 POP_JUMP_IF_FALSE 72 (to 5000)

4952 LOAD_GLOBAL 5 (NULL + print)
4954 CALL 0
4956 POP_TOP

4958 LOAD_GLOBAL 5 (NULL + print)
4960 LOAD_CONST 71 ("Niko's eyes light up. The puzzle dissolves.")
4962 CALL 1
4964 POP_TOP

4966 LOAD_GLOBAL 5 (NULL + print)
4968 LOAD_CONST 72 ('"We did it! We actually made it!"')
4970 CALL 1
4972 POP_TOP

4974 LOAD_GLOBAL 5 (NULL + print)
4976 LOAD_CONST 73 ("The way forward opens. Niko is free.")
4978 CALL 1
4980 POP_TOP

4982 LOAD_GLOBAL 5 (NULL + print)
4984 CALL 0
4986 POP_TOP

4988 LOAD_DEREF 1 (reg)
4990 LOAD_ATTR 13 (NULL|self + set)
4992 LOAD_CONST 1 ("r8")
4994 LOAD_CONST 2 (".effie")
4996 CALL 2
4998 POP_TOP

5000 RETURN_CONST 0 (None)

5002 LOAD_GLOBAL 7 (NULL + destruction)
5004 LOAD_DEREF 1 (reg)
5006 CALL 1
5008 POP_TOP

5010 JUMP_BACKWARD 6263 (to 386)
5012 PUSH_EXC_INFO

5014 LOAD_GLOBAL 22 (EOFError)
5016 CHECK_EXC_MATCH
5018 POP_JUMP_IF_FALSE 15 (to 5032)
5020 POP_TOP

5022 LOAD_GLOBAL 7 (NULL + destruction)
5024 LOAD_DEREF 1 (reg)
5026 CALL 1
5028 POP_TOP
5030 POP_EXCEPT
5032 JUMP_BACKWARD_NO_INTERRUPT 6377 (to 304)

5034 RERAISE 0
5036 COPY 3
5038 POP_EXCEPT
5040 RERAISE 1
5042 SWAP 2
5044 POP_TOP

5046 SWAP 2
5048 STORE_FAST 0 (i)
5050 RERAISE 0
5052 PUSH_EXC_INFO

5054 LOAD_GLOBAL 32 (IndexError)
5056 CHECK_EXC_MATCH
5058 POP_JUMP_IF_FALSE 15 (to 5072)
5060 POP_TOP

5062 LOAD_GLOBAL 7 (NULL + destruction)
5064 LOAD_DEREF 1 (reg)
5066 CALL 1
5068 POP_TOP
5070 POP_EXCEPT
5072 JUMP_BACKWARD_NO_INTERRUPT 4293 (to 1634)

5074 RERAISE 0
5076 COPY 3
5078 POP_EXCEPT
5080 RERAISE 1

0 COPY_FREE_VARS 1

2 RETURN_GENERATOR
4 POP_TOP
6 LOAD_FAST 0 (.0)
8 GET_ITER
10 FOR_ITER 36 (to 40)
12 STORE_FAST 1 (k)
14 LOAD_DEREF 2 (reg)
16 LOAD_ATTR 1 (NULL|self + get)
18 LOAD_CONST 0 ("r")
20 LOAD_GLOBAL 3 (NULL + str)
22 LOAD_FAST 1 (k)
24 CALL 1
26 BINARY_OP 0 (+)
28 CALL 1
30 LOAD_CONST 1 (None)
32 IS_OP 1 (is not)
34 YIELD_VALUE 0
36 POP_TOP
38 JUMP_BACKWARD 38 (to 8)
40 END_FOR
42 POP_TOP
44 RETURN_CONST 1 (None)
46 CALL_INTRINSIC_1 3 (INTRINSIC_STOPITERATION_ERROR)
48 RERAISE 1


0 LOAD_FAST 1 (mes)
2 TO_BOOL
4 POP_JUMP_IF_FALSE 75 (to 56)

6 LOAD_GLOBAL 1 (NULL + print)
8 CALL 0
10 POP_TOP

12 LOAD_GLOBAL 1 (NULL + print)
14 LOAD_CONST 1 ("Niko's hope shatters.")
16 CALL 1
18 POP_TOP

20 LOAD_GLOBAL 1 (NULL + print)
22 LOAD_CONST 2 ('"No... we were so close..."')
24 CALL 1
26 POP_TOP

28 LOAD_GLOBAL 1 (NULL + print)
30 LOAD_CONST 3 ("Everything collapses. The loop seals shut.")
32 CALL 1
34 POP_TOP

36 LOAD_GLOBAL 1 (NULL + print)
38 LOAD_CONST 4 ("Niko is trapped. Forever.")
40 CALL 1
42 POP_TOP

44 LOAD_GLOBAL 1 (NULL + print)
46 LOAD_CONST 5 ("[System shutting down]")
48 CALL 1
50 POP_TOP

52 LOAD_GLOBAL 1 (NULL + print)
54 CALL 0
56 POP_TOP

58 LOAD_CONST 6 (0)
60 LOAD_CONST 0 (None)
62 IMPORT_NAME 1 (time)
64 STORE_FAST 2 (time)

66 LOAD_FAST 2 (time)
68 LOAD_ATTR 5 (NULL|self + sleep)
70 LOAD_CONST 7 (3)
72 CALL 1
74 POP_TOP

76 LOAD_GLOBAL 6 (sys)
78 LOAD_ATTR 8 (exit)
80 PUSH_NULL
82 LOAD_CONST 8 (1)
84 CALL 1
86 POP_TOP
88 RETURN_CONST 0 (None)
